{
  "id_sptag": "-1501705937",
  "index_page": 0,
  "name_cl_sptag": "Pigeon",
  "name_parent": "Anime",
  "total_img": 3,
  "total_page": 0,
  "hc_lt_alb": "-760531221",
  "hc_lt_data_img": "-1802800279",
  "hc_lt_nortag": "693395911",
  "hc_lt_sptag": "-1434053974",
  "lt_alb": [
    {
      "id_alb": "63410260",
      "name_alb": "Anime",
      "total_img": 85314
    }
  ],
  "lt_data_img": [
    {
      "hc_lt_id_alb": "-824026795",
      "hc_lt_id_nortag": "-324199368",
      "hc_lt_id_sptag": "-1403616835",
      "id_img": "Vocaloid_696799_crop2608_287269472",
      "link_img": "UTb0sGqADnbLiHq9qhRMRkSRiLND0Tk7ctN8tpraiid3xX3dmHhx7IKmMZb//MGkj4XZDNBKRJjewcvuljqnSZVy4706IhQgSYlgwrgVRHU=",
      "thumb": "UTb0sGqADnbLiHq9qhRMRkSRiLND0Tk7ctN8tpraiid3xX3dmHhx7IKmMZb//MGkL5xtN7Sh0G80gAMSTDQ1HJVy4706IhQgSYlgwrgVRHU=",
      "lt_id_alb": [
        "63410260"
      ],
      "list_id_nortag": [
        "-324062098",
        "-1182628656"
      ],
      "lt_id_sptag": [
        "177416588",
        "-1216236529",
        "-587335586",
        "1443880616",
        "29436897",
        "-1910110731",
        "-353024394",
        "376240968",
        "-67611207",
        "-1450260536",
        "-1501705937",
        "929761085",
        "1541647243",
        "680065126",
        "1508952095",
        "1447453426",
        "1677155011",
        "-1046579185",
        "1078827483",
        "-1456680780",
        "1257535371"
      ]
    },
    {
      "hc_lt_id_alb": "-824026795",
      "hc_lt_id_nortag": "1238006946",
      "hc_lt_id_sptag": "1900365629",
      "id_img": "LoveLive_895983_crop2608_1219540211",
      "link_img": "UTb0sGqADnbLiHq9qhRMRkSRiLND0Tk7ctN8tpraiiffU2W0S10vOvPyVRL7xt3oukCei8BQnJmyFDntcUYC/5Vy4706IhQgSYlgwrgVRHU=",
      "thumb": "UTb0sGqADnbLiHq9qhRMRkSRiLND0Tk7ctN8tpraiiffU2W0S10vOvPyVRL7xt3oTuxP0kXXqAxvDQM/liI9a5Vy4706IhQgSYlgwrgVRHU=",
      "lt_id_alb": [
        "63410260"
      ],
      "list_id_nortag": [
        "-1182628656",
        "-403748301"
      ],
      "lt_id_sptag": [
        "1545739930",
        "81052085",
        "-2110936861",
        "-353024394",
        "-1686571485",
        "-1501705937",
        "-1353196196",
        "-260062140",
        "1011616107",
        "-1738080146",
        "1078827483"
      ]
    },
    {
      "hc_lt_id_alb": "-824026795",
      "hc_lt_id_nortag": "-1131068287",
      "hc_lt_id_sptag": "750735212",
      "id_img": "Original_951001_crop2608_925992412",
      "link_img": "UTb0sGqADnbLiHq9qhRMRkSRiLND0Tk7ctN8tpraiif16rszwN7Vt9VaYFSAgQ56/LzBTQJs1wW9c6w2RtJqepVy4706IhQgSYlgwrgVRHU=",
      "thumb": "UTb0sGqADnbLiHq9qhRMRkSRiLND0Tk7ctN8tpraiif16rszwN7Vt9VaYFSAgQ563vEZQb/q4icNbs/k7FFxrJVy4706IhQgSYlgwrgVRHU=",
      "lt_id_alb": [
        "63410260"
      ],
      "list_id_nortag": [
        "-1182628656"
      ],
      "lt_id_sptag": [
        "-510384823",
        "-353024394",
        "376240968",
        "-1686571485",
        "-1501705937",
        "-1331370225",
        "1078827483"
      ]
    }
  ],
  "lt_nortag": [
    {
      "id_nortag": "-1182628656",
      "name_cl_nortag": "Girls",
      "total_img": 68557,
      "name_parent": "Anime"
    },
    {
      "id_nortag": "-403748301",
      "name_cl_nortag": "Love Live",
      "total_img": 463,
      "name_parent": "Anime"
    },
    {
      "id_nortag": "-324062098",
      "name_cl_nortag": "Vocaloid",
      "total_img": 1338,
      "name_parent": "Anime"
    }
  ],
  "lt_sptag": [
    {
      "id_sptag": "-1910110731",
      "name_cl_sptag": "Animal",
      "name_parent": "Anime",
      "total": 42
    },
    {
      "id_sptag": "1447453426",
      "name_cl_sptag": "Bird",
      "name_parent": "Anime",
      "total": 95
    },
    {
      "id_sptag": "-67611207",
      "name_cl_sptag": "Blush",
      "name_parent": "Anime",
      "total": 893
    },
    {
      "id_sptag": "-587335586",
      "name_cl_sptag": "Camera",
      "name_parent": "Anime",
      "total": 19
    },
    {
      "id_sptag": "-1046579185",
      "name_cl_sptag": "Cat",
      "name_parent": "Anime",
      "total": 128
    },
    {
      "id_sptag": "376240968",
      "name_cl_sptag": "Girls Eyes Blue",
      "name_parent": "Anime",
      "total": 25656
    },
    {
      "id_sptag": "1545739930",
      "name_cl_sptag": "Girls Eyes Brown",
      "name_parent": "Anime",
      "total": 9376
    },
    {
      "id_sptag": "-1686571485",
      "name_cl_sptag": "Girls Hair Black",
      "name_parent": "Anime",
      "total": 16737
    },
    {
      "id_sptag": "-1450260536",
      "name_cl_sptag": "Girls Hair Blue",
      "name_parent": "Anime",
      "total": 9528
    },
    {
      "id_sptag": "-1353196196",
      "name_cl_sptag": "Girls Hair Orange",
      "name_parent": "Anime",
      "total": 4128
    },
    {
      "id_sptag": "-353024394",
      "name_cl_sptag": "Girls Long Hair",
      "name_parent": "Anime",
      "total": 47407
    },
    {
      "id_sptag": "81052085",
      "name_cl_sptag": "Girls Music",
      "name_parent": "Anime",
      "total": 1611
    },
    {
      "id_sptag": "680065126",
      "name_cl_sptag": "Girls Sad",
      "name_parent": "Anime",
      "total": 10506
    },
    {
      "id_sptag": "1541647243",
      "name_cl_sptag": "Girls Student",
      "name_parent": "Anime",
      "total": 16308
    },
    {
      "id_sptag": "1078827483",
      "name_cl_sptag": "Girls Tie Bows",
      "name_parent": "Anime",
      "total": 61257
    },
    {
      "id_sptag": "-260062140",
      "name_cl_sptag": "Girls Uniform",
      "name_parent": "Anime",
      "total": 16929
    },
    {
      "id_sptag": "1508952095",
      "name_cl_sptag": "Girls Water Rain",
      "name_parent": "Anime",
      "total": 2954
    },
    {
      "id_sptag": "1257535371",
      "name_cl_sptag": "Hatsune Miku",
      "name_parent": "Anime",
      "total": 884
    },
    {
      "id_sptag": "-2110936861",
      "name_cl_sptag": "Maki Nishikino",
      "name_parent": "Anime",
      "total": 258
    },
    {
      "id_sptag": "1011616107",
      "name_cl_sptag": "Nico Yazawa",
      "name_parent": "Anime",
      "total": 259
    },
    {
      "id_sptag": "1677155011",
      "name_cl_sptag": "Petal",
      "name_parent": "Anime",
      "total": 70
    },
    {
      "id_sptag": "-1501705937",
      "name_cl_sptag": "Pigeon",
      "name_parent": "Anime",
      "total": 3
    },
    {
      "id_sptag": "-1216236529",
      "name_cl_sptag": "Sad",
      "name_parent": "Anime",
      "total": 12057
    },
    {
      "id_sptag": "29436897",
      "name_cl_sptag": "School Uniform",
      "name_parent": "Anime",
      "total": 467
    },
    {
      "id_sptag": "177416588",
      "name_cl_sptag": "Skirt",
      "name_parent": "Anime",
      "total": 368
    },
    {
      "id_sptag": "1443880616",
      "name_cl_sptag": "Socks",
      "name_parent": "Anime",
      "total": 28
    },
    {
      "id_sptag": "-1331370225",
      "name_cl_sptag": "Sunset",
      "name_parent": "Anime",
      "total": 51
    },
    {
      "id_sptag": "-510384823",
      "name_cl_sptag": "Tail",
      "name_parent": "Anime",
      "total": 78
    },
    {
      "id_sptag": "-1456680780",
      "name_cl_sptag": "Twintails",
      "name_parent": "Anime",
      "total": 386
    },
    {
      "id_sptag": "929761085",
      "name_cl_sptag": "Umbrella",
      "name_parent": "Anime",
      "total": 120
    },
    {
      "id_sptag": "-1738080146",
      "name_cl_sptag": "Violinist",
      "name_parent": "Anime",
      "total": 5
    }
  ]
}