{
  "id_sptag": "-91513366",
  "index_page": 0,
  "name_cl_sptag": "Redhead",
  "name_parent": "Anime",
  "total_img": 4,
  "total_page": 0,
  "hc_lt_alb": "-760531221",
  "hc_lt_data_img": "-156449606",
  "hc_lt_nortag": "-1476597278",
  "hc_lt_sptag": "-811256947",
  "lt_alb": [
    {
      "id_alb": "63410260",
      "name_alb": "Anime",
      "total_img": 85314
    }
  ],
  "lt_data_img": [
    {
      "hc_lt_id_alb": "-824026795",
      "hc_lt_id_nortag": "1531712947",
      "hc_lt_id_sptag": "-1282179849",
      "id_img": "Original_708419_crop2608_-1230256355",
      "link_img": "UTb0sGqADnbLiHq9qhRMRkSRiLND0Tk7ctN8tpraiieJfElaikORb3m3PDAckgrXs8TqWtQKS9WUuVesV62FrZVy4706IhQgSYlgwrgVRHU=",
      "thumb": "UTb0sGqADnbLiHq9qhRMRkSRiLND0Tk7ctN8tpraiieJfElaikORb3m3PDAckgrXBLtNs1/+WVr95CLTPt1jl5Vy4706IhQgSYlgwrgVRHU=",
      "lt_id_alb": [
        "63410260"
      ],
      "list_id_nortag": [
        "766871050",
        "-1182628656"
      ],
      "lt_id_sptag": [
        "-91513366",
        "-1353196196",
        "1846426926",
        "1078827483",
        "1410951528"
      ]
    },
    {
      "hc_lt_id_alb": "-824026795",
      "hc_lt_id_nortag": "-1293409368",
      "hc_lt_id_sptag": "-270912361",
      "id_img": "Angel_746370_crop2608_1219108579",
      "link_img": "UTb0sGqADnbLiHq9qhRMRkSRiLND0Tk7ctN8tpraiicsgd0eDp2gXgHMY4okbZuyVA6fOyFXzUv6cpIRputKBJVy4706IhQgSYlgwrgVRHU=",
      "thumb": "UTb0sGqADnbLiHq9qhRMRkSRiLND0Tk7ctN8tpraiicsgd0eDp2gXgHMY4okbZuydBEQkx4OmbXv0eLTPIzMnZVy4706IhQgSYlgwrgVRHU=",
      "lt_id_alb": [
        "63410260"
      ],
      "list_id_nortag": [
        "1496378362",
        "-1182628656"
      ],
      "lt_id_sptag": [
        "-561045702",
        "177416588",
        "-1230434216",
        "-91513366",
        "376240968",
        "-1353196196",
        "2026891902",
        "-260062140",
        "-1331370225",
        "1078827483",
        "-1353313151",
        "1410951528"
      ]
    },
    {
      "hc_lt_id_alb": "-824026795",
      "hc_lt_id_nortag": "-1293409368",
      "hc_lt_id_sptag": "1458970387",
      "id_img": "Angel_670932_crop2608_-1969327481",
      "link_img": "UTb0sGqADnbLiHq9qhRMRkSRiLND0Tk7ctN8tpraiicMhmHfgJKP7T5pLAmTEmRAY3Zg1WXJ0eayQskYAHkvxpVy4706IhQgSYlgwrgVRHU=",
      "thumb": "UTb0sGqADnbLiHq9qhRMRkSRiLND0Tk7ctN8tpraiicMhmHfgJKP7T5pLAmTEmRASGkyPaRWLWnjfhTGsJsIt5Vy4706IhQgSYlgwrgVRHU=",
      "lt_id_alb": [
        "63410260"
      ],
      "list_id_nortag": [
        "1496378362",
        "-1182628656"
      ],
      "lt_id_sptag": [
        "-1038892260",
        "-714099484",
        "-1216236529",
        "-91513366",
        "325835566",
        "489705754",
        "-353024394",
        "1168591711",
        "680065126",
        "-2114154352",
        "1508952095",
        "-1353196196",
        "1467442292",
        "-1353313151",
        "-664091313"
      ]
    },
    {
      "hc_lt_id_alb": "-824026795",
      "hc_lt_id_nortag": "-1131068287",
      "hc_lt_id_sptag": "-1410507145",
      "id_img": "Women_195975_crop2608_1641522877",
      "link_img": "UTb0sGqADnbLiHq9qhRMRkSRiLND0Tk7ctN8tpraiidFdVdupwHr5XrvySJwieP0Oio/oxjw9CE0XpBqGJMOxZVy4706IhQgSYlgwrgVRHU=",
      "thumb": "UTb0sGqADnbLiHq9qhRMRkSRiLND0Tk7ctN8tpraiidFdVdupwHr5XrvySJwieP0u3PbE19EgDCokaeXOKTWHpVy4706IhQgSYlgwrgVRHU=",
      "lt_id_alb": [
        "63410260"
      ],
      "list_id_nortag": [
        "-1182628656"
      ],
      "lt_id_sptag": [
        "-220048903",
        "-91513366",
        "1813151526",
        "1078827483",
        "-1353313151",
        "1410951528"
      ]
    }
  ],
  "lt_nortag": [
    {
      "id_nortag": "1496378362",
      "name_cl_nortag": "Angel",
      "total_img": 60,
      "name_parent": "Anime"
    },
    {
      "id_nortag": "-1182628656",
      "name_cl_nortag": "Girls",
      "total_img": 68557,
      "name_parent": "Anime"
    },
    {
      "id_nortag": "766871050",
      "name_cl_nortag": "Original",
      "total_img": 1020,
      "name_parent": "Anime"
    }
  ],
  "lt_sptag": [
    {
      "id_sptag": "325835566",
      "name_cl_sptag": "Cloud",
      "name_parent": "Anime",
      "total": 163
    },
    {
      "id_sptag": "1168591711",
      "name_cl_sptag": "Fantasy",
      "name_parent": "Anime",
      "total": 83
    },
    {
      "id_sptag": "-1038892260",
      "name_cl_sptag": "Feather",
      "name_parent": "Anime",
      "total": 26
    },
    {
      "id_sptag": "1846426926",
      "name_cl_sptag": "Girls Ears Neko",
      "name_parent": "Anime",
      "total": 7031
    },
    {
      "id_sptag": "376240968",
      "name_cl_sptag": "Girls Eyes Blue",
      "name_parent": "Anime",
      "total": 25656
    },
    {
      "id_sptag": "-561045702",
      "name_cl_sptag": "Girls Glasses",
      "name_parent": "Anime",
      "total": 2385
    },
    {
      "id_sptag": "1813151526",
      "name_cl_sptag": "Girls Hair Brow",
      "name_parent": "Anime",
      "total": 13760
    },
    {
      "id_sptag": "-1353196196",
      "name_cl_sptag": "Girls Hair Orange",
      "name_parent": "Anime",
      "total": 4128
    },
    {
      "id_sptag": "-353024394",
      "name_cl_sptag": "Girls Long Hair",
      "name_parent": "Anime",
      "total": 47407
    },
    {
      "id_sptag": "680065126",
      "name_cl_sptag": "Girls Sad",
      "name_parent": "Anime",
      "total": 10506
    },
    {
      "id_sptag": "1410951528",
      "name_cl_sptag": "Girls Short Hair",
      "name_parent": "Anime",
      "total": 23769
    },
    {
      "id_sptag": "-1230434216",
      "name_cl_sptag": "Girls Smile",
      "name_parent": "Anime",
      "total": 24284
    },
    {
      "id_sptag": "1078827483",
      "name_cl_sptag": "Girls Tie Bows",
      "name_parent": "Anime",
      "total": 61257
    },
    {
      "id_sptag": "-260062140",
      "name_cl_sptag": "Girls Uniform",
      "name_parent": "Anime",
      "total": 16929
    },
    {
      "id_sptag": "1508952095",
      "name_cl_sptag": "Girls Water Rain",
      "name_parent": "Anime",
      "total": 2954
    },
    {
      "id_sptag": "-220048903",
      "name_cl_sptag": "Gun",
      "name_parent": "Anime",
      "total": 55
    },
    {
      "id_sptag": "-664091313",
      "name_cl_sptag": "Light",
      "name_parent": "Anime",
      "total": 46
    },
    {
      "id_sptag": "-91513366",
      "name_cl_sptag": "Redhead",
      "name_parent": "Anime",
      "total": 4
    },
    {
      "id_sptag": "-714099484",
      "name_cl_sptag": "Reflection",
      "name_parent": "Anime",
      "total": 44
    },
    {
      "id_sptag": "-1216236529",
      "name_cl_sptag": "Sad",
      "name_parent": "Anime",
      "total": 12057
    },
    {
      "id_sptag": "177416588",
      "name_cl_sptag": "Skirt",
      "name_parent": "Anime",
      "total": 368
    },
    {
      "id_sptag": "489705754",
      "name_cl_sptag": "Sky",
      "name_parent": "Anime",
      "total": 168
    },
    {
      "id_sptag": "2026891902",
      "name_cl_sptag": "Smartphone",
      "name_parent": "Anime",
      "total": 10
    },
    {
      "id_sptag": "1467442292",
      "name_cl_sptag": "Sunbeam",
      "name_parent": "Anime",
      "total": 23
    },
    {
      "id_sptag": "-1331370225",
      "name_cl_sptag": "Sunset",
      "name_parent": "Anime",
      "total": 51
    },
    {
      "id_sptag": "-2114154352",
      "name_cl_sptag": "Water",
      "name_parent": "Anime",
      "total": 98
    },
    {
      "id_sptag": "-1353313151",
      "name_cl_sptag": "Wings",
      "name_parent": "Anime",
      "total": 124
    }
  ]
}