{
  "id_sptag": "1057871277",
  "index_page": 0,
  "name_cl_sptag": "Noe Isurugi",
  "name_parent": "Anime",
  "total_img": 13,
  "total_page": 0,
  "hc_lt_alb": "-760531221",
  "hc_lt_data_img": "-1034428524",
  "hc_lt_nortag": "-2044621922",
  "hc_lt_sptag": "919413907",
  "lt_alb": [
    {
      "id_alb": "63410260",
      "name_alb": "Anime",
      "total_img": 85314
    }
  ],
  "lt_data_img": [
    {
      "hc_lt_id_alb": "-824026795",
      "hc_lt_id_nortag": "-71699374",
      "hc_lt_id_sptag": "1872378944",
      "id_img": "TrueTears_297560_crop2608_738632960",
      "link_img": "UTb0sGqADnbLiHq9qhRMRkSRiLND0Tk7ctN8tpraiidCs/D21MpiFmP+Qh/kkMjYU7S+As3NuhZpCZSoOYPvIZVy4706IhQgSYlgwrgVRHU=",
      "thumb": "UTb0sGqADnbLiHq9qhRMRkSRiLND0Tk7ctN8tpraiidCs/D21MpiFmP+Qh/kkMjYDoKIx3HOB6KSqpx6sQSR0JVy4706IhQgSYlgwrgVRHU=",
      "lt_id_alb": [
        "63410260"
      ],
      "list_id_nortag": [
        "1619722968",
        "-1182628656"
      ],
      "lt_id_sptag": [
        "-1915687819",
        "-1465791898",
        "-1937610099",
        "-1230434216",
        "1057871277",
        "376240968",
        "-1686571485",
        "1541647243",
        "1813151526",
        "1896292994",
        "1078827483",
        "1410951528"
      ]
    },
    {
      "hc_lt_id_alb": "-824026795",
      "hc_lt_id_nortag": "-71699374",
      "hc_lt_id_sptag": "-1260367175",
      "id_img": "TrueTears_231735_crop2608_-1253255702",
      "link_img": "UTb0sGqADnbLiHq9qhRMRkSRiLND0Tk7ctN8tpraiicLuqBnFoFvI2IP2UUmJ9h+xQc/GG+ptfJ628KQ4navsJVy4706IhQgSYlgwrgVRHU=",
      "thumb": "UTb0sGqADnbLiHq9qhRMRkSRiLND0Tk7ctN8tpraiicLuqBnFoFvI2IP2UUmJ9h+oH29hY4Wwkm7Z08Ojqy375Vy4706IhQgSYlgwrgVRHU=",
      "lt_id_alb": [
        "63410260"
      ],
      "list_id_nortag": [
        "1619722968",
        "-1182628656"
      ],
      "lt_id_sptag": [
        "-1465791898",
        "-1216236529",
        "1057871277",
        "376240968",
        "-1686571485",
        "680065126",
        "1813151526",
        "768898453",
        "1078827483",
        "1410951528"
      ]
    },
    {
      "hc_lt_id_alb": "-824026795",
      "hc_lt_id_nortag": "-71699374",
      "hc_lt_id_sptag": "-1003024602",
      "id_img": "TrueTears_231741_crop2608_-585202299",
      "link_img": "UTb0sGqADnbLiHq9qhRMRkSRiLND0Tk7ctN8tpraiieFmYyI5wa2ESMSH0DQjHpjoV8MgJwWunhH4CVDJVOYBJVy4706IhQgSYlgwrgVRHU=",
      "thumb": "UTb0sGqADnbLiHq9qhRMRkSRiLND0Tk7ctN8tpraiieFmYyI5wa2ESMSH0DQjHpj4ru3LhA1zINaYqsxQdIeQ5Vy4706IhQgSYlgwrgVRHU=",
      "lt_id_alb": [
        "63410260"
      ],
      "list_id_nortag": [
        "1619722968",
        "-1182628656"
      ],
      "lt_id_sptag": [
        "-1915687819",
        "-1465791898",
        "-1230434216",
        "1057871277",
        "-353024394",
        "376240968",
        "-1686571485",
        "1541647243",
        "1813151526",
        "1896292994",
        "-899599709",
        "1078827483",
        "1410951528"
      ]
    },
    {
      "hc_lt_id_alb": "-824026795",
      "hc_lt_id_nortag": "-71699374",
      "hc_lt_id_sptag": "195992265",
      "id_img": "TrueTears_231735_crop2608_1584447259",
      "link_img": "UTb0sGqADnbLiHq9qhRMRkSRiLND0Tk7ctN8tpraiieIXBcxuDi0jOURD8305kGagcIgBAG/M3uGLQjyVI3jkpVy4706IhQgSYlgwrgVRHU=",
      "thumb": "UTb0sGqADnbLiHq9qhRMRkSRiLND0Tk7ctN8tpraiieIXBcxuDi0jOURD8305kGaVW//oAix5R8oXnTUu+ENHZVy4706IhQgSYlgwrgVRHU=",
      "lt_id_alb": [
        "63410260"
      ],
      "list_id_nortag": [
        "1619722968",
        "-1182628656"
      ],
      "lt_id_sptag": [
        "-1465791898",
        "1057871277",
        "-353024394",
        "376240968",
        "1813151526",
        "768898453"
      ]
    },
    {
      "hc_lt_id_alb": "-824026795",
      "hc_lt_id_nortag": "-2022510395",
      "hc_lt_id_sptag": "1092761993",
      "id_img": "Crossover_715279_crop2608_179386857",
      "link_img": "UTb0sGqADnbLiHq9qhRMRkSRiLND0Tk7ctN8tpraiietxYQcyLnF5jfF8y8MP/vfeEpEPL3vYCijshRUcVc1s5Vy4706IhQgSYlgwrgVRHU=",
      "thumb": "UTb0sGqADnbLiHq9qhRMRkSRiLND0Tk7ctN8tpraiietxYQcyLnF5jfF8y8MP/vfjYnOiWP62aeEx0psWuRdb5Vy4706IhQgSYlgwrgVRHU=",
      "lt_id_alb": [
        "63410260"
      ],
      "list_id_nortag": [
        "1213914829"
      ],
      "lt_id_sptag": [
        "-1465791898",
        "799115661",
        "1057871277",
        "1896292994"
      ]
    },
    {
      "hc_lt_id_alb": "-824026795",
      "hc_lt_id_nortag": "-71699374",
      "hc_lt_id_sptag": "1142239984",
      "id_img": "TrueTears_267910_crop2608_941736934",
      "link_img": "UTb0sGqADnbLiHq9qhRMRkSRiLND0Tk7ctN8tpraiicA575WZD5RWcJPkflmBGHx5jmjWVtkvBXMx2/0jV1aRpVy4706IhQgSYlgwrgVRHU=",
      "thumb": "UTb0sGqADnbLiHq9qhRMRkSRiLND0Tk7ctN8tpraiicA575WZD5RWcJPkflmBGHxDUR5AMqFxN9XEo6Lkd5p9JVy4706IhQgSYlgwrgVRHU=",
      "lt_id_alb": [
        "63410260"
      ],
      "list_id_nortag": [
        "1619722968",
        "-1182628656"
      ],
      "lt_id_sptag": [
        "-1465791898",
        "750914149",
        "1057871277",
        "-353024394",
        "376240968",
        "1813151526",
        "1896292994",
        "1078827483"
      ]
    },
    {
      "hc_lt_id_alb": "-824026795",
      "hc_lt_id_nortag": "-2022510395",
      "hc_lt_id_sptag": "1092761993",
      "id_img": "Crossover_715279_crop2608_2077467286",
      "link_img": "UTb0sGqADnbLiHq9qhRMRkSRiLND0Tk7ctN8tpraiiexfBnxo5Q3cdl4DnUlChKRCRxywRYGVx+jfjNN0MZ79pVy4706IhQgSYlgwrgVRHU=",
      "thumb": "UTb0sGqADnbLiHq9qhRMRkSRiLND0Tk7ctN8tpraiiexfBnxo5Q3cdl4DnUlChKR+X9309zBmPOXa5J7I2GLwZVy4706IhQgSYlgwrgVRHU=",
      "lt_id_alb": [
        "63410260"
      ],
      "list_id_nortag": [
        "1213914829"
      ],
      "lt_id_sptag": [
        "-1465791898",
        "799115661",
        "1057871277",
        "1896292994"
      ]
    },
    {
      "hc_lt_id_alb": "-824026795",
      "hc_lt_id_nortag": "-71699374",
      "hc_lt_id_sptag": "-196619220",
      "id_img": "TrueTears_231741_crop2608_1746695986",
      "link_img": "UTb0sGqADnbLiHq9qhRMRkSRiLND0Tk7ctN8tpraiifgsptdxAgBstVlz4+7iLsyx8Iq2PxMOVG6aUztjcOf2ZVy4706IhQgSYlgwrgVRHU=",
      "thumb": "UTb0sGqADnbLiHq9qhRMRkSRiLND0Tk7ctN8tpraiifgsptdxAgBstVlz4+7iLsyzgXUL6Dpcs0GBu7JPVv+rZVy4706IhQgSYlgwrgVRHU=",
      "lt_id_alb": [
        "63410260"
      ],
      "list_id_nortag": [
        "1619722968",
        "-1182628656"
      ],
      "lt_id_sptag": [
        "-1915687819",
        "-1465791898",
        "-1230434216",
        "1057871277",
        "376240968",
        "-1686571485",
        "1541647243",
        "1813151526",
        "1896292994",
        "1078827483",
        "1410951528"
      ]
    },
    {
      "hc_lt_id_alb": "-824026795",
      "hc_lt_id_nortag": "-2022510395",
      "hc_lt_id_sptag": "1092761993",
      "id_img": "Crossover_715279_crop2608_-1248273668",
      "link_img": "UTb0sGqADnbLiHq9qhRMRkSRiLND0Tk7ctN8tpraiidQ+Zu72oKdplj/E3n5jJSGpUdP0gf99WjNlNY9W0ZGVJVy4706IhQgSYlgwrgVRHU=",
      "thumb": "UTb0sGqADnbLiHq9qhRMRkSRiLND0Tk7ctN8tpraiidQ+Zu72oKdplj/E3n5jJSGr/XfMVw8kL/Aa5GmEpwYpZVy4706IhQgSYlgwrgVRHU=",
      "lt_id_alb": [
        "63410260"
      ],
      "list_id_nortag": [
        "1213914829"
      ],
      "lt_id_sptag": [
        "-1465791898",
        "799115661",
        "1057871277",
        "1896292994"
      ]
    },
    {
      "hc_lt_id_alb": "-824026795",
      "hc_lt_id_nortag": "-71699374",
      "hc_lt_id_sptag": "1070760357",
      "id_img": "TrueTears_267910_crop2608_909742239",
      "link_img": "UTb0sGqADnbLiHq9qhRMRkSRiLND0Tk7ctN8tpraiidHQD16+2QPklh1aKeH9yHQv6XPvcdxo7m7XiIRD2vUC5Vy4706IhQgSYlgwrgVRHU=",
      "thumb": "UTb0sGqADnbLiHq9qhRMRkSRiLND0Tk7ctN8tpraiidHQD16+2QPklh1aKeH9yHQOLv9Tzej//95MxjhdN6DE5Vy4706IhQgSYlgwrgVRHU=",
      "lt_id_alb": [
        "63410260"
      ],
      "list_id_nortag": [
        "1619722968",
        "-1182628656"
      ],
      "lt_id_sptag": [
        "-1465791898",
        "750914149",
        "1057871277",
        "376240968",
        "-1686571485",
        "1896292994",
        "1078827483",
        "1410951528"
      ]
    },
    {
      "hc_lt_id_alb": "-824026795",
      "hc_lt_id_nortag": "-71699374",
      "hc_lt_id_sptag": "585681183",
      "id_img": "TrueTears_297560_crop2608_-1652907027",
      "link_img": "UTb0sGqADnbLiHq9qhRMRkSRiLND0Tk7ctN8tpraiicWa+CxiLuvFVkKOjtg9EWa4YlwXfoihFGa9LkCK3TcapVy4706IhQgSYlgwrgVRHU=",
      "thumb": "UTb0sGqADnbLiHq9qhRMRkSRiLND0Tk7ctN8tpraiicWa+CxiLuvFVkKOjtg9EWaa/jmcGl8OR8evPVhIRZuMpVy4706IhQgSYlgwrgVRHU=",
      "lt_id_alb": [
        "63410260"
      ],
      "list_id_nortag": [
        "1619722968",
        "-1182628656"
      ],
      "lt_id_sptag": [
        "-1915687819",
        "-1465791898",
        "-1230434216",
        "1057871277",
        "1541647243",
        "1813151526",
        "1896292994",
        "1078827483",
        "1410951528"
      ]
    },
    {
      "hc_lt_id_alb": "-824026795",
      "hc_lt_id_nortag": "-71699374",
      "hc_lt_id_sptag": "1151060044",
      "id_img": "TrueTears_297562_crop2608_-627480739",
      "link_img": "UTb0sGqADnbLiHq9qhRMRkSRiLND0Tk7ctN8tpraiidrCZbCf89ypMlauK1ri3w5hZHkCJRfU2k5gz0J6l9AUZVy4706IhQgSYlgwrgVRHU=",
      "thumb": "UTb0sGqADnbLiHq9qhRMRkSRiLND0Tk7ctN8tpraiidrCZbCf89ypMlauK1ri3w5ZWSHAUlccs/M55fxMiPHbpVy4706IhQgSYlgwrgVRHU=",
      "lt_id_alb": [
        "63410260"
      ],
      "list_id_nortag": [
        "1619722968",
        "-1182628656"
      ],
      "lt_id_sptag": [
        "-1915687819",
        "-1465791898",
        "1057871277",
        "-353024394",
        "376240968",
        "-1686571485",
        "1813151526",
        "1896292994",
        "768898453",
        "1078827483",
        "1410951528"
      ]
    },
    {
      "hc_lt_id_alb": "-824026795",
      "hc_lt_id_nortag": "-71699374",
      "hc_lt_id_sptag": "1801795881",
      "id_img": "TrueTears_297560_crop2608_-1091513659",
      "link_img": "UTb0sGqADnbLiHq9qhRMRkSRiLND0Tk7ctN8tpraiicsDuKvgS+jgGt+R63YLuYQJnTw7xwHuTHhsGX8Nr3it5Vy4706IhQgSYlgwrgVRHU=",
      "thumb": "UTb0sGqADnbLiHq9qhRMRkSRiLND0Tk7ctN8tpraiicsDuKvgS+jgGt+R63YLuYQ2EgTMRZVYuVAJ7VQZLoRjpVy4706IhQgSYlgwrgVRHU=",
      "lt_id_alb": [
        "63410260"
      ],
      "list_id_nortag": [
        "1619722968",
        "-1182628656"
      ],
      "lt_id_sptag": [
        "-1465791898",
        "1057871277",
        "-353024394",
        "376240968",
        "-1686571485",
        "1541647243",
        "1813151526",
        "1896292994",
        "1078827483"
      ]
    }
  ],
  "lt_nortag": [
    {
      "id_nortag": "1213914829",
      "name_cl_nortag": "Crossover",
      "total_img": 505,
      "name_parent": "Anime"
    },
    {
      "id_nortag": "-1182628656",
      "name_cl_nortag": "Girls",
      "total_img": 68557,
      "name_parent": "Anime"
    },
    {
      "id_nortag": "1619722968",
      "name_cl_nortag": "True Tears",
      "total_img": 14,
      "name_parent": "Anime"
    }
  ],
  "lt_sptag": [
    {
      "id_sptag": "1896292994",
      "name_cl_sptag": "Aiko Andou",
      "name_parent": "Anime",
      "total": 11
    },
    {
      "id_sptag": "-899599709",
      "name_cl_sptag": "Girls Eyes Black",
      "name_parent": "Anime",
      "total": 5810
    },
    {
      "id_sptag": "376240968",
      "name_cl_sptag": "Girls Eyes Blue",
      "name_parent": "Anime",
      "total": 25656
    },
    {
      "id_sptag": "-1915687819",
      "name_cl_sptag": "Girls Eyes Red",
      "name_parent": "Anime",
      "total": 12697
    },
    {
      "id_sptag": "-1686571485",
      "name_cl_sptag": "Girls Hair Black",
      "name_parent": "Anime",
      "total": 16737
    },
    {
      "id_sptag": "1813151526",
      "name_cl_sptag": "Girls Hair Brow",
      "name_parent": "Anime",
      "total": 13760
    },
    {
      "id_sptag": "-1937610099",
      "name_cl_sptag": "Girls Hair Grey",
      "name_parent": "Anime",
      "total": 9239
    },
    {
      "id_sptag": "750914149",
      "name_cl_sptag": "Girls Kimono Yukata Cheongsam",
      "name_parent": "Anime",
      "total": 7942
    },
    {
      "id_sptag": "-353024394",
      "name_cl_sptag": "Girls Long Hair",
      "name_parent": "Anime",
      "total": 47407
    },
    {
      "id_sptag": "680065126",
      "name_cl_sptag": "Girls Sad",
      "name_parent": "Anime",
      "total": 10506
    },
    {
      "id_sptag": "768898453",
      "name_cl_sptag": "Girls Scarf",
      "name_parent": "Anime",
      "total": 3306
    },
    {
      "id_sptag": "1410951528",
      "name_cl_sptag": "Girls Short Hair",
      "name_parent": "Anime",
      "total": 23769
    },
    {
      "id_sptag": "-1230434216",
      "name_cl_sptag": "Girls Smile",
      "name_parent": "Anime",
      "total": 24284
    },
    {
      "id_sptag": "1541647243",
      "name_cl_sptag": "Girls Student",
      "name_parent": "Anime",
      "total": 16308
    },
    {
      "id_sptag": "1078827483",
      "name_cl_sptag": "Girls Tie Bows",
      "name_parent": "Anime",
      "total": 61257
    },
    {
      "id_sptag": "-1465791898",
      "name_cl_sptag": "Hiromi Yuasa",
      "name_parent": "Anime",
      "total": 13
    },
    {
      "id_sptag": "1057871277",
      "name_cl_sptag": "Noe Isurugi",
      "name_parent": "Anime",
      "total": 13
    },
    {
      "id_sptag": "799115661",
      "name_cl_sptag": "Ohana Matsumae",
      "name_parent": "Anime",
      "total": 28
    },
    {
      "id_sptag": "-1216236529",
      "name_cl_sptag": "Sad",
      "name_parent": "Anime",
      "total": 12057
    }
  ]
}