{
  "id_sptag": "1939660094",
  "index_page": 0,
  "name_cl_sptag": "Rikka Takarada",
  "name_parent": "Anime",
  "total_img": 5,
  "total_page": 0,
  "hc_lt_alb": "-760531221",
  "hc_lt_data_img": "1740769103",
  "hc_lt_nortag": "1102464",
  "hc_lt_sptag": "-966613220",
  "lt_alb": [
    {
      "id_alb": "63410260",
      "name_alb": "Anime",
      "total_img": 85314
    }
  ],
  "lt_data_img": [
    {
      "hc_lt_id_alb": "-824026795",
      "hc_lt_id_nortag": "1379968352",
      "hc_lt_id_sptag": "707443350",
      "id_img": "SSSSGridman_979166_crop2608_749114145",
      "link_img": "UTb0sGqADnbLiHq9qhRMRkSRiLND0Tk7ctN8tpraiifWdO+il/xBXJWoo69aumVLkjPjPN8unzXw2xDwlgvkNJVy4706IhQgSYlgwrgVRHU=",
      "thumb": "UTb0sGqADnbLiHq9qhRMRkSRiLND0Tk7ctN8tpraiifWdO+il/xBXJWoo69aumVLUVY4/dGKQEEjCE0wepyRb5Vy4706IhQgSYlgwrgVRHU=",
      "lt_id_alb": [
        "63410260"
      ],
      "list_id_nortag": [
        "-1680016906",
        "-1882392243"
      ],
      "lt_id_sptag": [
        "-1680016906",
        "1939660094"
      ]
    },
    {
      "hc_lt_id_alb": "-824026795",
      "hc_lt_id_nortag": "-1681331630",
      "hc_lt_id_sptag": "35805480",
      "id_img": "SSSSGridman_960744_crop2608_747928207",
      "link_img": "UTb0sGqADnbLiHq9qhRMRkSRiLND0Tk7ctN8tpraiicZ1XbJgdpwlrJhUr27wsDX9OcQggqeDj+EnEU/C4g1sJVy4706IhQgSYlgwrgVRHU=",
      "thumb": "UTb0sGqADnbLiHq9qhRMRkSRiLND0Tk7ctN8tpraiicZ1XbJgdpwlrJhUr27wsDXdO8+amWvrf0CM4UTefHNe5Vy4706IhQgSYlgwrgVRHU=",
      "lt_id_alb": [
        "63410260"
      ],
      "list_id_nortag": [
        "-1182628656",
        "-1882392243"
      ],
      "lt_id_sptag": [
        "-1915687819",
        "-1230434216",
        "-353024394",
        "376240968",
        "-1686571485",
        "1939660094",
        "1541647243",
        "1078827483",
        "-1358769180"
      ]
    },
    {
      "hc_lt_id_alb": "-824026795",
      "hc_lt_id_nortag": "-1681331630",
      "hc_lt_id_sptag": "-399935181",
      "id_img": "SSSSGridman_957028_crop2608_747206438",
      "link_img": "UTb0sGqADnbLiHq9qhRMRkSRiLND0Tk7ctN8tpraiidJisJHpZZmuTp6D7HW1Rdr3Iw3ZnHYJ4zpbW++qbC1wpVy4706IhQgSYlgwrgVRHU=",
      "thumb": "UTb0sGqADnbLiHq9qhRMRkSRiLND0Tk7ctN8tpraiidJisJHpZZmuTp6D7HW1RdrYIyByM4stzrz8fMwFXeOKpVy4706IhQgSYlgwrgVRHU=",
      "lt_id_alb": [
        "63410260"
      ],
      "list_id_nortag": [
        "-1182628656",
        "-1882392243"
      ],
      "lt_id_sptag": [
        "-1543681642",
        "376240968",
        "-1686571485",
        "-67611207",
        "1939660094",
        "1541647243",
        "1078827483",
        "491824726",
        "1410951528"
      ]
    },
    {
      "hc_lt_id_alb": "-824026795",
      "hc_lt_id_nortag": "-1681331630",
      "hc_lt_id_sptag": "-293972313",
      "id_img": "SSSSGridman_960715_crop2608_747928115",
      "link_img": "UTb0sGqADnbLiHq9qhRMRkSRiLND0Tk7ctN8tpraiid5PmwgV6nM2vV8YdQgqPV/yFAPWTdLEeOb5m8bRPW1y5Vy4706IhQgSYlgwrgVRHU=",
      "thumb": "UTb0sGqADnbLiHq9qhRMRkSRiLND0Tk7ctN8tpraiid5PmwgV6nM2vV8YdQgqPV/b8S55vKSNV58DOBmWH8HZpVy4706IhQgSYlgwrgVRHU=",
      "lt_id_alb": [
        "63410260"
      ],
      "list_id_nortag": [
        "-1182628656",
        "-1882392243"
      ],
      "lt_id_sptag": [
        "81052085",
        "-353024394",
        "376240968",
        "-1686571485",
        "1939660094",
        "1541647243",
        "1078827483"
      ]
    },
    {
      "hc_lt_id_alb": "-824026795",
      "hc_lt_id_nortag": "-1681331630",
      "hc_lt_id_sptag": "36415638",
      "id_img": "SSSSGridman_970503_crop2608_748849681",
      "link_img": "UTb0sGqADnbLiHq9qhRMRkSRiLND0Tk7ctN8tpraiieViFnX9l4JiQOzHUBiurLFnv7uH4Ls8bQrKv3ayPYbQ5Vy4706IhQgSYlgwrgVRHU=",
      "thumb": "UTb0sGqADnbLiHq9qhRMRkSRiLND0Tk7ctN8tpraiieViFnX9l4JiQOzHUBiurLFPrTbYFwPPnmvOwyFqyYAu5Vy4706IhQgSYlgwrgVRHU=",
      "lt_id_alb": [
        "63410260"
      ],
      "list_id_nortag": [
        "-1182628656",
        "-1882392243"
      ],
      "lt_id_sptag": [
        "-1230434216",
        "-353024394",
        "376240968",
        "-1450260536",
        "1939660094",
        "1541647243",
        "1078827483"
      ]
    }
  ],
  "lt_nortag": [
    {
      "id_nortag": "-1182628656",
      "name_cl_nortag": "Girls",
      "total_img": 68557,
      "name_parent": "Anime"
    },
    {
      "id_nortag": "-1680016906",
      "name_cl_nortag": "Scenery Arts",
      "total_img": 2036,
      "name_parent": "Anime"
    },
    {
      "id_nortag": "-1882392243",
      "name_cl_nortag": "SSSSGridman",
      "total_img": 5,
      "name_parent": "Anime"
    }
  ],
  "lt_sptag": [
    {
      "id_sptag": "-67611207",
      "name_cl_sptag": "Blush",
      "name_parent": "Anime",
      "total": 893
    },
    {
      "id_sptag": "-1543681642",
      "name_cl_sptag": "Face",
      "name_parent": "Anime",
      "total": 58
    },
    {
      "id_sptag": "491824726",
      "name_cl_sptag": "Girls Cute Cool",
      "name_parent": "Anime",
      "total": 31431
    },
    {
      "id_sptag": "376240968",
      "name_cl_sptag": "Girls Eyes Blue",
      "name_parent": "Anime",
      "total": 25656
    },
    {
      "id_sptag": "-1915687819",
      "name_cl_sptag": "Girls Eyes Red",
      "name_parent": "Anime",
      "total": 12697
    },
    {
      "id_sptag": "-1686571485",
      "name_cl_sptag": "Girls Hair Black",
      "name_parent": "Anime",
      "total": 16737
    },
    {
      "id_sptag": "-1450260536",
      "name_cl_sptag": "Girls Hair Blue",
      "name_parent": "Anime",
      "total": 9528
    },
    {
      "id_sptag": "-1358769180",
      "name_cl_sptag": "Girls Hair Pink",
      "name_parent": "Anime",
      "total": 5690
    },
    {
      "id_sptag": "-353024394",
      "name_cl_sptag": "Girls Long Hair",
      "name_parent": "Anime",
      "total": 47407
    },
    {
      "id_sptag": "81052085",
      "name_cl_sptag": "Girls Music",
      "name_parent": "Anime",
      "total": 1611
    },
    {
      "id_sptag": "1410951528",
      "name_cl_sptag": "Girls Short Hair",
      "name_parent": "Anime",
      "total": 23769
    },
    {
      "id_sptag": "-1230434216",
      "name_cl_sptag": "Girls Smile",
      "name_parent": "Anime",
      "total": 24284
    },
    {
      "id_sptag": "1541647243",
      "name_cl_sptag": "Girls Student",
      "name_parent": "Anime",
      "total": 16308
    },
    {
      "id_sptag": "1078827483",
      "name_cl_sptag": "Girls Tie Bows",
      "name_parent": "Anime",
      "total": 61257
    },
    {
      "id_sptag": "1939660094",
      "name_cl_sptag": "Rikka Takarada",
      "name_parent": "Anime",
      "total": 5
    },
    {
      "id_sptag": "-1680016906",
      "name_cl_sptag": "Scenery Arts",
      "name_parent": "Anime",
      "total": 2036
    }
  ]
}