{
  "id_sptag": "235131583",
  "index_page": 0,
  "name_cl_sptag": "Minato Namikaze",
  "name_parent": "Anime",
  "total_img": 43,
  "total_page": 0,
  "hc_lt_alb": "-760531221",
  "hc_lt_data_img": "61356501",
  "hc_lt_nortag": "1768745663",
  "hc_lt_sptag": "1938114987",
  "lt_alb": [
    {
      "id_alb": "63410260",
      "name_alb": "Anime",
      "total_img": 85314
    }
  ],
  "lt_data_img": [
    {
      "hc_lt_id_alb": "-824026795",
      "hc_lt_id_nortag": "-2022510395",
      "hc_lt_id_sptag": "1332432109",
      "id_img": "Crossover_833321_crop2608_-1885622569",
      "link_img": "UTb0sGqADnbLiHq9qhRMRkSRiLND0Tk7ctN8tpraiidrW9lfTpS8oKFMYNC3ExANB9xZ65Xih3gOkeyhHiu555Vy4706IhQgSYlgwrgVRHU=",
      "thumb": "UTb0sGqADnbLiHq9qhRMRkSRiLND0Tk7ctN8tpraiidrW9lfTpS8oKFMYNC3ExANFQu8rS4xS6He48hthWwWJ5Vy4706IhQgSYlgwrgVRHU=",
      "lt_id_alb": [
        "63410260"
      ],
      "list_id_nortag": [
        "1213914829"
      ],
      "lt_id_sptag": [
        "-916379327",
        "-1936986648",
        "2080340491",
        "154930047",
        "-1287948517",
        "1031977212",
        "-91316480",
        "1097983947",
        "-1491861316",
        "433369509",
        "1686539664",
        "-1282606609",
        "-555297640",
        "182755482",
        "-1236345551",
        "1169337322",
        "6278890",
        "120588791",
        "253689623",
        "1341791943",
        "-855277766",
        "636212748",
        "1767521621",
        "2037558530",
        "-1102714022",
        "-1019873723",
        "175619851",
        "-2029145421",
        "758979432",
        "1171821264",
        "941027275",
        "1977786894",
        "-266713074",
        "-1619220508",
        "-1052321700",
        "1753469251",
        "1233261441",
        "1510416678",
        "87064186",
        "-336629613",
        "-1477452695",
        "755798438",
        "235131583",
        "1304638402",
        "644020459",
        "1484744413",
        "-247566452",
        "1275572979",
        "-1777120776",
        "-678729605"
      ]
    },
    {
      "hc_lt_id_alb": "-824026795",
      "hc_lt_id_nortag": "551849679",
      "hc_lt_id_sptag": "-1026671811",
      "id_img": "Naruto_106861_crop2608_-161758609",
      "link_img": "UTb0sGqADnbLiHq9qhRMRkSRiLND0Tk7ctN8tpraiidqy2ofNssMrjciIhiDtbkdLsRKAZ72Vu7F4CezgMdCt5Vy4706IhQgSYlgwrgVRHU=",
      "thumb": "UTb0sGqADnbLiHq9qhRMRkSRiLND0Tk7ctN8tpraiidqy2ofNssMrjciIhiDtbkdIlJsrNySwAu9QF9vnATel5Vy4706IhQgSYlgwrgVRHU=",
      "lt_id_alb": [
        "63410260"
      ],
      "list_id_nortag": [
        "-273690518"
      ],
      "lt_id_sptag": [
        "-1147068729",
        "636212748",
        "707334961",
        "235131583"
      ]
    },
    {
      "hc_lt_id_alb": "-824026795",
      "hc_lt_id_nortag": "551849679",
      "hc_lt_id_sptag": "-2112967895",
      "id_img": "Naruto_755701_crop2608_-1636277420",
      "link_img": "UTb0sGqADnbLiHq9qhRMRkSRiLND0Tk7ctN8tpraiieESvriGRwjr++kB7lv2biXRYGLQ6xApgY+pBSdelNdD5Vy4706IhQgSYlgwrgVRHU=",
      "thumb": "UTb0sGqADnbLiHq9qhRMRkSRiLND0Tk7ctN8tpraiieESvriGRwjr++kB7lv2biXRzE/ZLukJfkkU/vemrcQx5Vy4706IhQgSYlgwrgVRHU=",
      "lt_id_alb": [
        "63410260"
      ],
      "list_id_nortag": [
        "-273690518"
      ],
      "lt_id_sptag": [
        "-1282606609",
        "1083705889",
        "-1424398522",
        "636212748",
        "707334961",
        "-1812796880",
        "235131583"
      ]
    },
    {
      "hc_lt_id_alb": "-824026795",
      "hc_lt_id_nortag": "551849679",
      "hc_lt_id_sptag": "1503467993",
      "id_img": "Naruto_154832_crop2608_1225825451",
      "link_img": "UTb0sGqADnbLiHq9qhRMRkSRiLND0Tk7ctN8tpraiien8hVQvdlB8AS653I8KPGgXetZYezQThwCmSsaRUrZUJVy4706IhQgSYlgwrgVRHU=",
      "thumb": "UTb0sGqADnbLiHq9qhRMRkSRiLND0Tk7ctN8tpraiien8hVQvdlB8AS653I8KPGghL4l19knGsaaqfhsmXrE35Vy4706IhQgSYlgwrgVRHU=",
      "lt_id_alb": [
        "63410260"
      ],
      "list_id_nortag": [
        "-273690518"
      ],
      "lt_id_sptag": [
        "-313914664",
        "120588791",
        "636212748",
        "-2029145421",
        "235131583"
      ]
    },
    {
      "hc_lt_id_alb": "-824026795",
      "hc_lt_id_nortag": "551849679",
      "hc_lt_id_sptag": "2145115468",
      "id_img": "Naruto_744734_crop2608_950450801",
      "link_img": "UTb0sGqADnbLiHq9qhRMRkSRiLND0Tk7ctN8tpraiicWAOC5Zs7zpxjToq8VN+auSOuPOKOappMElCsD8Ym0xJVy4706IhQgSYlgwrgVRHU=",
      "thumb": "UTb0sGqADnbLiHq9qhRMRkSRiLND0Tk7ctN8tpraiicWAOC5Zs7zpxjToq8VN+auBS2ZarPoDnvohlz8StVPS5Vy4706IhQgSYlgwrgVRHU=",
      "lt_id_alb": [
        "63410260"
      ],
      "list_id_nortag": [
        "-273690518"
      ],
      "lt_id_sptag": [
        "-1147068729",
        "-313914664",
        "-1680871127",
        "-762518597",
        "-2029145421",
        "-2123925318",
        "235131583",
        "-1636146762"
      ]
    },
    {
      "hc_lt_id_alb": "-824026795",
      "hc_lt_id_nortag": "551849679",
      "hc_lt_id_sptag": "2145115468",
      "id_img": "Naruto_744734_crop2608_-580970540",
      "link_img": "UTb0sGqADnbLiHq9qhRMRkSRiLND0Tk7ctN8tpraiideMEQRD6mjxPBq6qsWU02UPyC+F14Srv+uQH7ol6uVl5Vy4706IhQgSYlgwrgVRHU=",
      "thumb": "UTb0sGqADnbLiHq9qhRMRkSRiLND0Tk7ctN8tpraiideMEQRD6mjxPBq6qsWU02UdbdDyPndQDEW3ctaNRQDKpVy4706IhQgSYlgwrgVRHU=",
      "lt_id_alb": [
        "63410260"
      ],
      "list_id_nortag": [
        "-273690518"
      ],
      "lt_id_sptag": [
        "-1147068729",
        "-313914664",
        "-1680871127",
        "-762518597",
        "-2029145421",
        "-2123925318",
        "235131583",
        "-1636146762"
      ]
    },
    {
      "hc_lt_id_alb": "-824026795",
      "hc_lt_id_nortag": "795716792",
      "hc_lt_id_sptag": "-40309642",
      "id_img": "Crossover_713933_crop2608_-2048328867",
      "link_img": "UTb0sGqADnbLiHq9qhRMRkSRiLND0Tk7ctN8tpraiicpAdpAqVWjFD4AdF6ukhlYyMH7CplSdFGQmaVRK1X16JVy4706IhQgSYlgwrgVRHU=",
      "thumb": "UTb0sGqADnbLiHq9qhRMRkSRiLND0Tk7ctN8tpraiicpAdpAqVWjFD4AdF6ukhlYRACkFryQan/j+siX8rwQG5Vy4706IhQgSYlgwrgVRHU=",
      "lt_id_alb": [
        "63410260"
      ],
      "list_id_nortag": [
        "-467032699",
        "1213914829"
      ],
      "lt_id_sptag": [
        "235131583",
        "-1612103380"
      ]
    },
    {
      "hc_lt_id_alb": "-824026795",
      "hc_lt_id_nortag": "-2022510395",
      "hc_lt_id_sptag": "1332432109",
      "id_img": "Crossover_833321_crop2608_2087568027",
      "link_img": "UTb0sGqADnbLiHq9qhRMRkSRiLND0Tk7ctN8tpraiifDtSIUWB5eoaRJ1CGkPk1q5FSGQG6LUcO2g1znHXbhu5Vy4706IhQgSYlgwrgVRHU=",
      "thumb": "UTb0sGqADnbLiHq9qhRMRkSRiLND0Tk7ctN8tpraiifDtSIUWB5eoaRJ1CGkPk1qtJ/qLW6ZW35swcKWM4yrsZVy4706IhQgSYlgwrgVRHU=",
      "lt_id_alb": [
        "63410260"
      ],
      "list_id_nortag": [
        "1213914829"
      ],
      "lt_id_sptag": [
        "-916379327",
        "-1936986648",
        "2080340491",
        "154930047",
        "-1287948517",
        "1031977212",
        "-91316480",
        "1097983947",
        "-1491861316",
        "433369509",
        "1686539664",
        "-1282606609",
        "-555297640",
        "182755482",
        "-1236345551",
        "1169337322",
        "6278890",
        "120588791",
        "253689623",
        "1341791943",
        "-855277766",
        "636212748",
        "1767521621",
        "2037558530",
        "-1102714022",
        "-1019873723",
        "175619851",
        "-2029145421",
        "758979432",
        "1171821264",
        "941027275",
        "1977786894",
        "-266713074",
        "-1619220508",
        "-1052321700",
        "1753469251",
        "1233261441",
        "1510416678",
        "87064186",
        "-336629613",
        "-1477452695",
        "755798438",
        "235131583",
        "1304638402",
        "644020459",
        "1484744413",
        "-247566452",
        "1275572979",
        "-1777120776",
        "-678729605"
      ]
    },
    {
      "hc_lt_id_alb": "-824026795",
      "hc_lt_id_nortag": "551849679",
      "hc_lt_id_sptag": "1586095232",
      "id_img": "Naruto_135625_crop2608_-1724846772",
      "link_img": "UTb0sGqADnbLiHq9qhRMRkSRiLND0Tk7ctN8tpraiichvV/BAvRhAakaHV4Of6UjZgQY/2QoLetKfqxSacHB0pVy4706IhQgSYlgwrgVRHU=",
      "thumb": "UTb0sGqADnbLiHq9qhRMRkSRiLND0Tk7ctN8tpraiichvV/BAvRhAakaHV4Of6Ujf66yygNKzES0+6C1um8L0JVy4706IhQgSYlgwrgVRHU=",
      "lt_id_alb": [
        "63410260"
      ],
      "list_id_nortag": [
        "-273690518"
      ],
      "lt_id_sptag": [
        "-1282606609",
        "120588791",
        "636212748",
        "707334961",
        "-1812796880",
        "235131583"
      ]
    },
    {
      "hc_lt_id_alb": "-824026795",
      "hc_lt_id_nortag": "551849679",
      "hc_lt_id_sptag": "1586095232",
      "id_img": "Naruto_135625_crop2608_-2052743783",
      "link_img": "UTb0sGqADnbLiHq9qhRMRkSRiLND0Tk7ctN8tpraiieD/+b+iMcI+dd3oD2PXuVzRiHmMR5Atd6M/QEn4GQ/wZVy4706IhQgSYlgwrgVRHU=",
      "thumb": "UTb0sGqADnbLiHq9qhRMRkSRiLND0Tk7ctN8tpraiieD/+b+iMcI+dd3oD2PXuVzPMo+xzCbsyKIBYuunI95oZVy4706IhQgSYlgwrgVRHU=",
      "lt_id_alb": [
        "63410260"
      ],
      "list_id_nortag": [
        "-273690518"
      ],
      "lt_id_sptag": [
        "-1282606609",
        "120588791",
        "636212748",
        "707334961",
        "-1812796880",
        "235131583"
      ]
    },
    {
      "hc_lt_id_alb": "-824026795",
      "hc_lt_id_nortag": "-2022510395",
      "hc_lt_id_sptag": "-19086149",
      "id_img": "Crossover_740459_crop2608_-2066694187",
      "link_img": "UTb0sGqADnbLiHq9qhRMRkSRiLND0Tk7ctN8tpraiifIBkbhbPX0DkAXLe/YP5l3GcYOe63CKvRiwoN2cnqjb5Vy4706IhQgSYlgwrgVRHU=",
      "thumb": "UTb0sGqADnbLiHq9qhRMRkSRiLND0Tk7ctN8tpraiifIBkbhbPX0DkAXLe/YP5l33QpyZGbogH1RzOQOKmMHcJVy4706IhQgSYlgwrgVRHU=",
      "lt_id_alb": [
        "63410260"
      ],
      "list_id_nortag": [
        "1213914829"
      ],
      "lt_id_sptag": [
        "2080340491",
        "1031977212",
        "1097983947",
        "1278412262",
        "-1236345551",
        "-1194486571",
        "-1989109578",
        "-456927585",
        "105837710",
        "1339472867",
        "1171821264",
        "1483714349",
        "-1619220508",
        "707334961",
        "-1052321700",
        "-1986334657",
        "-1812796880",
        "-1477452695",
        "-356011767",
        "235131583",
        "-1566457957",
        "1428433125",
        "-1092878010"
      ]
    },
    {
      "hc_lt_id_alb": "-824026795",
      "hc_lt_id_nortag": "-924890430",
      "hc_lt_id_sptag": "-244900748",
      "id_img": "Naruto_606237_crop2608_1067123034",
      "link_img": "UTb0sGqADnbLiHq9qhRMRkSRiLND0Tk7ctN8tpraiifBeWhMQ36+T2dacUGPrQfugxhqJ+L86f1k538aPRLNYZVy4706IhQgSYlgwrgVRHU=",
      "thumb": "UTb0sGqADnbLiHq9qhRMRkSRiLND0Tk7ctN8tpraiifBeWhMQ36+T2dacUGPrQfulbR4xUYyRTzSTPV2sIzqOZVy4706IhQgSYlgwrgVRHU=",
      "lt_id_alb": [
        "63410260"
      ],
      "list_id_nortag": [
        "-467032699",
        "-273690518"
      ],
      "lt_id_sptag": [
        "235131583"
      ]
    },
    {
      "hc_lt_id_alb": "-824026795",
      "hc_lt_id_nortag": "-243299809",
      "hc_lt_id_sptag": "-116912138",
      "id_img": "Naruto_267344_crop2608_1548571040",
      "link_img": "UTb0sGqADnbLiHq9qhRMRkSRiLND0Tk7ctN8tpraiifsgIZz8QVUCJpbYS8ok5Oyq09hll5IQk6cttN/mFCYt5Vy4706IhQgSYlgwrgVRHU=",
      "thumb": "UTb0sGqADnbLiHq9qhRMRkSRiLND0Tk7ctN8tpraiifsgIZz8QVUCJpbYS8ok5Oybq59l1brNNgR4DJSep1yOZVy4706IhQgSYlgwrgVRHU=",
      "lt_id_alb": [
        "63410260"
      ],
      "list_id_nortag": [
        "1728965817",
        "-273690518"
      ],
      "lt_id_sptag": [
        "-313914664",
        "235131583"
      ]
    },
    {
      "hc_lt_id_alb": "-824026795",
      "hc_lt_id_nortag": "795716792",
      "hc_lt_id_sptag": "-40309642",
      "id_img": "Crossover_713933_crop2608_-1935553195",
      "link_img": "UTb0sGqADnbLiHq9qhRMRkSRiLND0Tk7ctN8tpraiiewxj8xPvGXpJ3wtgH5b0QiH7Y2GSRIwQdAvwOea6bC65Vy4706IhQgSYlgwrgVRHU=",
      "thumb": "UTb0sGqADnbLiHq9qhRMRkSRiLND0Tk7ctN8tpraiiewxj8xPvGXpJ3wtgH5b0QiAvYudKAtoV27s2yogBXOtpVy4706IhQgSYlgwrgVRHU=",
      "lt_id_alb": [
        "63410260"
      ],
      "list_id_nortag": [
        "-467032699",
        "1213914829"
      ],
      "lt_id_sptag": [
        "235131583",
        "-1612103380"
      ]
    },
    {
      "hc_lt_id_alb": "-824026795",
      "hc_lt_id_nortag": "-924890430",
      "hc_lt_id_sptag": "1419959239",
      "id_img": "Naruto_954102_crop2608_-1157095909",
      "link_img": "UTb0sGqADnbLiHq9qhRMRkSRiLND0Tk7ctN8tpraiic/UlipCisR5jmfkvBpGFJoGLKELjAiedHQd+OHGfDCe5Vy4706IhQgSYlgwrgVRHU=",
      "thumb": "UTb0sGqADnbLiHq9qhRMRkSRiLND0Tk7ctN8tpraiic/UlipCisR5jmfkvBpGFJo/kKvK5tC34ZlFy+YCJc6VJVy4706IhQgSYlgwrgVRHU=",
      "lt_id_alb": [
        "63410260"
      ],
      "list_id_nortag": [
        "-467032699",
        "-273690518"
      ],
      "lt_id_sptag": [
        "1956034203",
        "-1216236529",
        "235131583"
      ]
    },
    {
      "hc_lt_id_alb": "-824026795",
      "hc_lt_id_nortag": "551849679",
      "hc_lt_id_sptag": "590273854",
      "id_img": "Naruto_735708_crop2608_337723782",
      "link_img": "UTb0sGqADnbLiHq9qhRMRkSRiLND0Tk7ctN8tpraiiemhpO+tN+22PNVoCBCayua4GMrm/yvwFC1LeyEkD6nzZVy4706IhQgSYlgwrgVRHU=",
      "thumb": "UTb0sGqADnbLiHq9qhRMRkSRiLND0Tk7ctN8tpraiiemhpO+tN+22PNVoCBCayuaMy0Sw1RXU/cswUODyodX9pVy4706IhQgSYlgwrgVRHU=",
      "lt_id_alb": [
        "63410260"
      ],
      "list_id_nortag": [
        "-273690518"
      ],
      "lt_id_sptag": [
        "759287130",
        "-1147068729",
        "-1282606609",
        "-1732733924",
        "1390001312",
        "120588791",
        "636212748",
        "-2029145421",
        "-437830348",
        "-1812796880",
        "235131583",
        "639891871",
        "-1777120776"
      ]
    },
    {
      "hc_lt_id_alb": "-824026795",
      "hc_lt_id_nortag": "551849679",
      "hc_lt_id_sptag": "-2112967895",
      "id_img": "Naruto_755701_crop2608_-1699291407",
      "link_img": "UTb0sGqADnbLiHq9qhRMRkSRiLND0Tk7ctN8tpraiidh0GOKR2U4XE1XT7EMhOP5EIAOrdIT0lWPyqZ1OVJLqJVy4706IhQgSYlgwrgVRHU=",
      "thumb": "UTb0sGqADnbLiHq9qhRMRkSRiLND0Tk7ctN8tpraiidh0GOKR2U4XE1XT7EMhOP5+Vk+fDNMkQiEEuFTe1NW9pVy4706IhQgSYlgwrgVRHU=",
      "lt_id_alb": [
        "63410260"
      ],
      "list_id_nortag": [
        "-273690518"
      ],
      "lt_id_sptag": [
        "-1282606609",
        "1083705889",
        "-1424398522",
        "636212748",
        "707334961",
        "-1812796880",
        "235131583"
      ]
    },
    {
      "hc_lt_id_alb": "-824026795",
      "hc_lt_id_nortag": "-924890430",
      "hc_lt_id_sptag": "1419959239",
      "id_img": "Naruto_788694_crop2608_-1674307974",
      "link_img": "UTb0sGqADnbLiHq9qhRMRkSRiLND0Tk7ctN8tpraiiest+hMXpgov83+ptWuUa5GyFDzx8ZcDuWP2vN+slpj+JVy4706IhQgSYlgwrgVRHU=",
      "thumb": "UTb0sGqADnbLiHq9qhRMRkSRiLND0Tk7ctN8tpraiiest+hMXpgov83+ptWuUa5GnKopRBTgfDUHhTqhqtyQgZVy4706IhQgSYlgwrgVRHU=",
      "lt_id_alb": [
        "63410260"
      ],
      "list_id_nortag": [
        "-467032699",
        "-273690518"
      ],
      "lt_id_sptag": [
        "1956034203",
        "-1216236529",
        "235131583"
      ]
    },
    {
      "hc_lt_id_alb": "-824026795",
      "hc_lt_id_nortag": "-924890430",
      "hc_lt_id_sptag": "-244900748",
      "id_img": "Naruto_950483_crop2608_19433691",
      "link_img": "UTb0sGqADnbLiHq9qhRMRkSRiLND0Tk7ctN8tpraiiehFQFnXm1tOySQIEvQptSRAHT8X5/+qgVz7iiF+ZLolZVy4706IhQgSYlgwrgVRHU=",
      "thumb": "UTb0sGqADnbLiHq9qhRMRkSRiLND0Tk7ctN8tpraiiehFQFnXm1tOySQIEvQptSRZ8OUcS25xrcZqcU7DkfsO5Vy4706IhQgSYlgwrgVRHU=",
      "lt_id_alb": [
        "63410260"
      ],
      "list_id_nortag": [
        "-467032699",
        "-273690518"
      ],
      "lt_id_sptag": [
        "235131583"
      ]
    },
    {
      "hc_lt_id_alb": "-824026795",
      "hc_lt_id_nortag": "551849679",
      "hc_lt_id_sptag": "-1026671811",
      "id_img": "Naruto_106861_crop2608_1061118774",
      "link_img": "UTb0sGqADnbLiHq9qhRMRkSRiLND0Tk7ctN8tpraiicTlc8ou0JAEZn8v6d2JdL5+JmPKKn2kpE7yuu7uXMqgJVy4706IhQgSYlgwrgVRHU=",
      "thumb": "UTb0sGqADnbLiHq9qhRMRkSRiLND0Tk7ctN8tpraiicTlc8ou0JAEZn8v6d2JdL5LoY2kJ07yNieAQ3xH5E/+5Vy4706IhQgSYlgwrgVRHU=",
      "lt_id_alb": [
        "63410260"
      ],
      "list_id_nortag": [
        "-273690518"
      ],
      "lt_id_sptag": [
        "-1147068729",
        "636212748",
        "707334961",
        "235131583"
      ]
    },
    {
      "hc_lt_id_alb": "-824026795",
      "hc_lt_id_nortag": "551849679",
      "hc_lt_id_sptag": "2145115468",
      "id_img": "Naruto_744734_crop2608_1518449089",
      "link_img": "UTb0sGqADnbLiHq9qhRMRkSRiLND0Tk7ctN8tpraiidt1DEwgJo594606g10fhZ8cxuudPwp+B/6hGitMwsFppVy4706IhQgSYlgwrgVRHU=",
      "thumb": "UTb0sGqADnbLiHq9qhRMRkSRiLND0Tk7ctN8tpraiidt1DEwgJo594606g10fhZ8ZA56aBRhRqmrLdw0nKk9mpVy4706IhQgSYlgwrgVRHU=",
      "lt_id_alb": [
        "63410260"
      ],
      "list_id_nortag": [
        "-273690518"
      ],
      "lt_id_sptag": [
        "-1147068729",
        "-313914664",
        "-1680871127",
        "-762518597",
        "-2029145421",
        "-2123925318",
        "235131583",
        "-1636146762"
      ]
    },
    {
      "hc_lt_id_alb": "-824026795",
      "hc_lt_id_nortag": "551849679",
      "hc_lt_id_sptag": "236584482",
      "id_img": "Naruto_744727_crop2608_-2038295899",
      "link_img": "UTb0sGqADnbLiHq9qhRMRkSRiLND0Tk7ctN8tpraiic5XjBSjKpSmAdhGhmMzqXBO26BYy4XUVySpdVCgKdNQ5Vy4706IhQgSYlgwrgVRHU=",
      "thumb": "UTb0sGqADnbLiHq9qhRMRkSRiLND0Tk7ctN8tpraiic5XjBSjKpSmAdhGhmMzqXB4tkUiEOxJfRykixw5z1iRJVy4706IhQgSYlgwrgVRHU=",
      "lt_id_alb": [
        "63410260"
      ],
      "list_id_nortag": [
        "-273690518"
      ],
      "lt_id_sptag": [
        "-1147068729",
        "-1282606609",
        "120588791",
        "636212748",
        "-2029145421",
        "707334961",
        "235131583"
      ]
    },
    {
      "hc_lt_id_alb": "-824026795",
      "hc_lt_id_nortag": "-2022510395",
      "hc_lt_id_sptag": "1332432109",
      "id_img": "Crossover_833321_crop2608_702636650",
      "link_img": "UTb0sGqADnbLiHq9qhRMRkSRiLND0Tk7ctN8tpraiifJQSkRwqaE09C9tAwhw8d4uKKZi8Bq2PjYM1wDIfP2oZVy4706IhQgSYlgwrgVRHU=",
      "thumb": "UTb0sGqADnbLiHq9qhRMRkSRiLND0Tk7ctN8tpraiifJQSkRwqaE09C9tAwhw8d48F6B0hfNJPIxkcEqZixfO5Vy4706IhQgSYlgwrgVRHU=",
      "lt_id_alb": [
        "63410260"
      ],
      "list_id_nortag": [
        "1213914829"
      ],
      "lt_id_sptag": [
        "-916379327",
        "-1936986648",
        "2080340491",
        "154930047",
        "-1287948517",
        "1031977212",
        "-91316480",
        "1097983947",
        "-1491861316",
        "433369509",
        "1686539664",
        "-1282606609",
        "-555297640",
        "182755482",
        "-1236345551",
        "1169337322",
        "6278890",
        "120588791",
        "253689623",
        "1341791943",
        "-855277766",
        "636212748",
        "1767521621",
        "2037558530",
        "-1102714022",
        "-1019873723",
        "175619851",
        "-2029145421",
        "758979432",
        "1171821264",
        "941027275",
        "1977786894",
        "-266713074",
        "-1619220508",
        "-1052321700",
        "1753469251",
        "1233261441",
        "1510416678",
        "87064186",
        "-336629613",
        "-1477452695",
        "755798438",
        "235131583",
        "1304638402",
        "644020459",
        "1484744413",
        "-247566452",
        "1275572979",
        "-1777120776",
        "-678729605"
      ]
    },
    {
      "hc_lt_id_alb": "-824026795",
      "hc_lt_id_nortag": "-924890430",
      "hc_lt_id_sptag": "-1026671811",
      "id_img": "Naruto_573553_crop2608_-1458368912",
      "link_img": "UTb0sGqADnbLiHq9qhRMRkSRiLND0Tk7ctN8tpraiifQulUWY/UJIZark70K/jukqUcVz0ZL0fVbriE8jzZ0AJVy4706IhQgSYlgwrgVRHU=",
      "thumb": "UTb0sGqADnbLiHq9qhRMRkSRiLND0Tk7ctN8tpraiifQulUWY/UJIZark70K/jukTsBxiZzpe+1riqHgFTcPWZVy4706IhQgSYlgwrgVRHU=",
      "lt_id_alb": [
        "63410260"
      ],
      "list_id_nortag": [
        "-467032699",
        "-273690518"
      ],
      "lt_id_sptag": [
        "-1147068729",
        "636212748",
        "707334961",
        "235131583"
      ]
    },
    {
      "hc_lt_id_alb": "-824026795",
      "hc_lt_id_nortag": "551849679",
      "hc_lt_id_sptag": "-441939935",
      "id_img": "Naruto_744714_crop2608_-2064652817",
      "link_img": "UTb0sGqADnbLiHq9qhRMRkSRiLND0Tk7ctN8tpraiicv4sm+D4XalEOqcRRTh/AxwSJXCHNFoHOF4OCM/XzmZJVy4706IhQgSYlgwrgVRHU=",
      "thumb": "UTb0sGqADnbLiHq9qhRMRkSRiLND0Tk7ctN8tpraiicv4sm+D4XalEOqcRRTh/AxiKVnrkOzJsCTFqUDdEVyiZVy4706IhQgSYlgwrgVRHU=",
      "lt_id_alb": [
        "63410260"
      ],
      "list_id_nortag": [
        "-273690518"
      ],
      "lt_id_sptag": [
        "707334961",
        "-1812796880",
        "235131583"
      ]
    },
    {
      "hc_lt_id_alb": "-824026795",
      "hc_lt_id_nortag": "551849679",
      "hc_lt_id_sptag": "-1579263420",
      "id_img": "Naruto_673911_crop2608_-404037625",
      "link_img": "UTb0sGqADnbLiHq9qhRMRkSRiLND0Tk7ctN8tpraiie/y/JKs4L9q4hhzP0jm4E3eDdWo1iUk6vYaILeyxSuXpVy4706IhQgSYlgwrgVRHU=",
      "thumb": "UTb0sGqADnbLiHq9qhRMRkSRiLND0Tk7ctN8tpraiie/y/JKs4L9q4hhzP0jm4E354Ai/PrS9d+IKaRNk0XPnJVy4706IhQgSYlgwrgVRHU=",
      "lt_id_alb": [
        "63410260"
      ],
      "list_id_nortag": [
        "-273690518"
      ],
      "lt_id_sptag": [
        "-313914664",
        "-567684239",
        "636212748",
        "235131583"
      ]
    },
    {
      "hc_lt_id_alb": "-824026795",
      "hc_lt_id_nortag": "551849679",
      "hc_lt_id_sptag": "-441939935",
      "id_img": "Naruto_744714_crop2608_430146710",
      "link_img": "UTb0sGqADnbLiHq9qhRMRkSRiLND0Tk7ctN8tpraiieGje/RJICrLf9IX5fu2/bOdVDizP21wMCDoJcgLI1+TZVy4706IhQgSYlgwrgVRHU=",
      "thumb": "UTb0sGqADnbLiHq9qhRMRkSRiLND0Tk7ctN8tpraiieGje/RJICrLf9IX5fu2/bOTFGebLGkQRZPSn1tqEtzL5Vy4706IhQgSYlgwrgVRHU=",
      "lt_id_alb": [
        "63410260"
      ],
      "list_id_nortag": [
        "-273690518"
      ],
      "lt_id_sptag": [
        "707334961",
        "-1812796880",
        "235131583"
      ]
    },
    {
      "hc_lt_id_alb": "-824026795",
      "hc_lt_id_nortag": "-924890430",
      "hc_lt_id_sptag": "-1230541944",
      "id_img": "Naruto_705563_crop2608_-543569572",
      "link_img": "UTb0sGqADnbLiHq9qhRMRkSRiLND0Tk7ctN8tpraiidgONch26A3MCLsASEouFHGDSwrNQKrRGfIzQZjIxwxQ5Vy4706IhQgSYlgwrgVRHU=",
      "thumb": "UTb0sGqADnbLiHq9qhRMRkSRiLND0Tk7ctN8tpraiidgONch26A3MCLsASEouFHGgtT1yNcIrRhcjvehR42OMZVy4706IhQgSYlgwrgVRHU=",
      "lt_id_alb": [
        "63410260"
      ],
      "list_id_nortag": [
        "-467032699",
        "-273690518"
      ],
      "lt_id_sptag": [
        "-801134466",
        "235131583"
      ]
    },
    {
      "hc_lt_id_alb": "-824026795",
      "hc_lt_id_nortag": "-924890430",
      "hc_lt_id_sptag": "-244900748",
      "id_img": "Naruto_644177_crop2608_582901147",
      "link_img": "UTb0sGqADnbLiHq9qhRMRkSRiLND0Tk7ctN8tpraiifgXUkTiiJtP0maBdwlWUgiD5BmWoa8cf6i26Vz1UWJ2pVy4706IhQgSYlgwrgVRHU=",
      "thumb": "UTb0sGqADnbLiHq9qhRMRkSRiLND0Tk7ctN8tpraiifgXUkTiiJtP0maBdwlWUgi5/IK9YiPQPH1WmdrdNhIpZVy4706IhQgSYlgwrgVRHU=",
      "lt_id_alb": [
        "63410260"
      ],
      "list_id_nortag": [
        "-467032699",
        "-273690518"
      ],
      "lt_id_sptag": [
        "235131583"
      ]
    },
    {
      "hc_lt_id_alb": "-824026795",
      "hc_lt_id_nortag": "-924890430",
      "hc_lt_id_sptag": "-1230541944",
      "id_img": "Naruto_705563_crop2608_2141781897",
      "link_img": "UTb0sGqADnbLiHq9qhRMRkSRiLND0Tk7ctN8tpraiie0ndBT2drZvqRdclx6UOoiaM8QKsD8Fzxa1GBob0jLTJVy4706IhQgSYlgwrgVRHU=",
      "thumb": "UTb0sGqADnbLiHq9qhRMRkSRiLND0Tk7ctN8tpraiie0ndBT2drZvqRdclx6UOoi52ieHi0NpKiwlrokTftNjJVy4706IhQgSYlgwrgVRHU=",
      "lt_id_alb": [
        "63410260"
      ],
      "list_id_nortag": [
        "-467032699",
        "-273690518"
      ],
      "lt_id_sptag": [
        "-801134466",
        "235131583"
      ]
    },
    {
      "hc_lt_id_alb": "-824026795",
      "hc_lt_id_nortag": "795716792",
      "hc_lt_id_sptag": "-40309642",
      "id_img": "Crossover_713933_crop2608_-1643898768",
      "link_img": "UTb0sGqADnbLiHq9qhRMRkSRiLND0Tk7ctN8tpraiieOxOm4leLAK1yGp+d85ZatAS+VDuB8haLvjUi6jf8km5Vy4706IhQgSYlgwrgVRHU=",
      "thumb": "UTb0sGqADnbLiHq9qhRMRkSRiLND0Tk7ctN8tpraiieOxOm4leLAK1yGp+d85ZatTjhtZQIkvE6DygGge5R5p5Vy4706IhQgSYlgwrgVRHU=",
      "lt_id_alb": [
        "63410260"
      ],
      "list_id_nortag": [
        "-467032699",
        "1213914829"
      ],
      "lt_id_sptag": [
        "235131583",
        "-1612103380"
      ]
    },
    {
      "hc_lt_id_alb": "-824026795",
      "hc_lt_id_nortag": "551849679",
      "hc_lt_id_sptag": "-1358426291",
      "id_img": "Naruto_215797_crop2608_-2031570753",
      "link_img": "UTb0sGqADnbLiHq9qhRMRkSRiLND0Tk7ctN8tpraiidLad2oed/VhdeLxtylCBv1aHxTKrrQZpjz9M7DP+L4ppVy4706IhQgSYlgwrgVRHU=",
      "thumb": "UTb0sGqADnbLiHq9qhRMRkSRiLND0Tk7ctN8tpraiidLad2oed/VhdeLxtylCBv1XjXpt/k9w4kz0VslmUWq+JVy4706IhQgSYlgwrgVRHU=",
      "lt_id_alb": [
        "63410260"
      ],
      "list_id_nortag": [
        "-273690518"
      ],
      "lt_id_sptag": [
        "-2020568135",
        "235131583",
        "319237405"
      ]
    },
    {
      "hc_lt_id_alb": "-824026795",
      "hc_lt_id_nortag": "551849679",
      "hc_lt_id_sptag": "-1358426291",
      "id_img": "Naruto_216841_crop2608_421961214",
      "link_img": "UTb0sGqADnbLiHq9qhRMRkSRiLND0Tk7ctN8tpraiidevxU4RERfnTn5WigFgAToasGuzcZwocCI/lS5rODUtJVy4706IhQgSYlgwrgVRHU=",
      "thumb": "UTb0sGqADnbLiHq9qhRMRkSRiLND0Tk7ctN8tpraiidevxU4RERfnTn5WigFgAToWJcFUWzQngUaGTIxnzAOKZVy4706IhQgSYlgwrgVRHU=",
      "lt_id_alb": [
        "63410260"
      ],
      "list_id_nortag": [
        "-273690518"
      ],
      "lt_id_sptag": [
        "-2020568135",
        "235131583",
        "319237405"
      ]
    },
    {
      "hc_lt_id_alb": "-824026795",
      "hc_lt_id_nortag": "551849679",
      "hc_lt_id_sptag": "-2081195949",
      "id_img": "Naruto_636019_crop2608_-136740001",
      "link_img": "UTb0sGqADnbLiHq9qhRMRkSRiLND0Tk7ctN8tpraiidxJF9qwBcR7pftFQIIli8oTSgSrIzbLPk64owASbacy5Vy4706IhQgSYlgwrgVRHU=",
      "thumb": "UTb0sGqADnbLiHq9qhRMRkSRiLND0Tk7ctN8tpraiidxJF9qwBcR7pftFQIIli8oCrDrp/xcGtu/J16IPK19D5Vy4706IhQgSYlgwrgVRHU=",
      "lt_id_alb": [
        "63410260"
      ],
      "list_id_nortag": [
        "-273690518"
      ],
      "lt_id_sptag": [
        "-313914664",
        "636212748",
        "235131583"
      ]
    },
    {
      "hc_lt_id_alb": "-824026795",
      "hc_lt_id_nortag": "-2022510395",
      "hc_lt_id_sptag": "-19086149",
      "id_img": "Crossover_740459_crop2608_2137658000",
      "link_img": "UTb0sGqADnbLiHq9qhRMRkSRiLND0Tk7ctN8tpraiieytokGg06VeyzS+ZoWBcfZnIMlX8Z7O7XAJRSDsDhKAZVy4706IhQgSYlgwrgVRHU=",
      "thumb": "UTb0sGqADnbLiHq9qhRMRkSRiLND0Tk7ctN8tpraiieytokGg06VeyzS+ZoWBcfZ9Ff8FGGhrq4B2mQde3L4RpVy4706IhQgSYlgwrgVRHU=",
      "lt_id_alb": [
        "63410260"
      ],
      "list_id_nortag": [
        "1213914829"
      ],
      "lt_id_sptag": [
        "2080340491",
        "1031977212",
        "1097983947",
        "1278412262",
        "-1236345551",
        "-1194486571",
        "-1989109578",
        "-456927585",
        "105837710",
        "1339472867",
        "1171821264",
        "1483714349",
        "-1619220508",
        "707334961",
        "-1052321700",
        "-1986334657",
        "-1812796880",
        "-1477452695",
        "-356011767",
        "235131583",
        "-1566457957",
        "1428433125",
        "-1092878010"
      ]
    },
    {
      "hc_lt_id_alb": "-824026795",
      "hc_lt_id_nortag": "-924890430",
      "hc_lt_id_sptag": "-244900748",
      "id_img": "Naruto_332700_crop2608_1493757861",
      "link_img": "UTb0sGqADnbLiHq9qhRMRkSRiLND0Tk7ctN8tpraiicgfh0rvBTlJSijWQjSQXqTyq+u17BtNdP2BLa7e+wE25Vy4706IhQgSYlgwrgVRHU=",
      "thumb": "UTb0sGqADnbLiHq9qhRMRkSRiLND0Tk7ctN8tpraiicgfh0rvBTlJSijWQjSQXqTIFdia3qFsG5SFurhl+bMC5Vy4706IhQgSYlgwrgVRHU=",
      "lt_id_alb": [
        "63410260"
      ],
      "list_id_nortag": [
        "-467032699",
        "-273690518"
      ],
      "lt_id_sptag": [
        "235131583"
      ]
    },
    {
      "hc_lt_id_alb": "-824026795",
      "hc_lt_id_nortag": "551849679",
      "hc_lt_id_sptag": "-441939935",
      "id_img": "Naruto_744714_crop2608_-1755449853",
      "link_img": "UTb0sGqADnbLiHq9qhRMRkSRiLND0Tk7ctN8tpraiif+Wpo8jvG7lwKQGargejRngosuRf2avAsS6QacrueLTpVy4706IhQgSYlgwrgVRHU=",
      "thumb": "UTb0sGqADnbLiHq9qhRMRkSRiLND0Tk7ctN8tpraiif+Wpo8jvG7lwKQGargejRnaqPlLkOu6uDssLs4LNBu1ZVy4706IhQgSYlgwrgVRHU=",
      "lt_id_alb": [
        "63410260"
      ],
      "list_id_nortag": [
        "-273690518"
      ],
      "lt_id_sptag": [
        "707334961",
        "-1812796880",
        "235131583"
      ]
    },
    {
      "hc_lt_id_alb": "-824026795",
      "hc_lt_id_nortag": "551849679",
      "hc_lt_id_sptag": "-1579263420",
      "id_img": "Naruto_673911_crop2608_1303060378",
      "link_img": "UTb0sGqADnbLiHq9qhRMRkSRiLND0Tk7ctN8tpraiidj7CRVPez5we4AdEIdsBuTMmfKEAVtgUA8JpgS0vOZb5Vy4706IhQgSYlgwrgVRHU=",
      "thumb": "UTb0sGqADnbLiHq9qhRMRkSRiLND0Tk7ctN8tpraiidj7CRVPez5we4AdEIdsBuTYUFY8VlrcItWxCGUjNW8RZVy4706IhQgSYlgwrgVRHU=",
      "lt_id_alb": [
        "63410260"
      ],
      "list_id_nortag": [
        "-273690518"
      ],
      "lt_id_sptag": [
        "-313914664",
        "-567684239",
        "636212748",
        "235131583"
      ]
    },
    {
      "hc_lt_id_alb": "-824026795",
      "hc_lt_id_nortag": "-924890430",
      "hc_lt_id_sptag": "1419959239",
      "id_img": "Naruto_644177_crop2608_781724503",
      "link_img": "UTb0sGqADnbLiHq9qhRMRkSRiLND0Tk7ctN8tpraiifo6U/vdlZ02Oie1GIgC28uPx5QUUa1ulhHbh/gM2aAPpVy4706IhQgSYlgwrgVRHU=",
      "thumb": "UTb0sGqADnbLiHq9qhRMRkSRiLND0Tk7ctN8tpraiifo6U/vdlZ02Oie1GIgC28u7c/A6OtE1/EQfYGf2B35P5Vy4706IhQgSYlgwrgVRHU=",
      "lt_id_alb": [
        "63410260"
      ],
      "list_id_nortag": [
        "-467032699",
        "-273690518"
      ],
      "lt_id_sptag": [
        "1956034203",
        "-1216236529",
        "235131583"
      ]
    },
    {
      "hc_lt_id_alb": "-824026795",
      "hc_lt_id_nortag": "551849679",
      "hc_lt_id_sptag": "-1579263420",
      "id_img": "Naruto_673911_crop2608_-774132885",
      "link_img": "UTb0sGqADnbLiHq9qhRMRkSRiLND0Tk7ctN8tpraiidKge/bA05K3fxnYH0yA2Jhy5ayeJ4AcpkXIl8zGAp/dpVy4706IhQgSYlgwrgVRHU=",
      "thumb": "UTb0sGqADnbLiHq9qhRMRkSRiLND0Tk7ctN8tpraiidKge/bA05K3fxnYH0yA2JhwwSiThDbAdEYw2g+JjmMFZVy4706IhQgSYlgwrgVRHU=",
      "lt_id_alb": [
        "63410260"
      ],
      "list_id_nortag": [
        "-273690518"
      ],
      "lt_id_sptag": [
        "-313914664",
        "-567684239",
        "636212748",
        "235131583"
      ]
    },
    {
      "hc_lt_id_alb": "-824026795",
      "hc_lt_id_nortag": "551849679",
      "hc_lt_id_sptag": "-1026671811",
      "id_img": "Naruto_106861_crop2608_654188956",
      "link_img": "UTb0sGqADnbLiHq9qhRMRkSRiLND0Tk7ctN8tpraiicDKvJmtSAX5lhtr5UwHquBVvNAlxHhWeRLsBkV4XqINpVy4706IhQgSYlgwrgVRHU=",
      "thumb": "UTb0sGqADnbLiHq9qhRMRkSRiLND0Tk7ctN8tpraiicDKvJmtSAX5lhtr5UwHquBLxZKYC3kB/lY7AiTe3YC/5Vy4706IhQgSYlgwrgVRHU=",
      "lt_id_alb": [
        "63410260"
      ],
      "list_id_nortag": [
        "-273690518"
      ],
      "lt_id_sptag": [
        "-1147068729",
        "636212748",
        "707334961",
        "235131583"
      ]
    },
    {
      "hc_lt_id_alb": "-824026795",
      "hc_lt_id_nortag": "-924890430",
      "hc_lt_id_sptag": "-1026671811",
      "id_img": "Naruto_573553_crop2608_-2044147723",
      "link_img": "UTb0sGqADnbLiHq9qhRMRkSRiLND0Tk7ctN8tpraiicTzbCx3yhgPOmM7Ki/OehYqM5TYHMkl+n83oG/o0rtw5Vy4706IhQgSYlgwrgVRHU=",
      "thumb": "UTb0sGqADnbLiHq9qhRMRkSRiLND0Tk7ctN8tpraiicTzbCx3yhgPOmM7Ki/OehYXfCSFLtZiWVCfVj5vnrGw5Vy4706IhQgSYlgwrgVRHU=",
      "lt_id_alb": [
        "63410260"
      ],
      "list_id_nortag": [
        "-467032699",
        "-273690518"
      ],
      "lt_id_sptag": [
        "-1147068729",
        "636212748",
        "707334961",
        "235131583"
      ]
    },
    {
      "hc_lt_id_alb": "-824026795",
      "hc_lt_id_nortag": "-924890430",
      "hc_lt_id_sptag": "-1026671811",
      "id_img": "Naruto_573553_crop2608_-140517982",
      "link_img": "UTb0sGqADnbLiHq9qhRMRkSRiLND0Tk7ctN8tpraiieSq+2NXEjESvw/4PPYOVEI662xWrn8AU8pSkeK0P3V0ZVy4706IhQgSYlgwrgVRHU=",
      "thumb": "UTb0sGqADnbLiHq9qhRMRkSRiLND0Tk7ctN8tpraiieSq+2NXEjESvw/4PPYOVEIOGYREuxsc1OhNlGupP5Ep5Vy4706IhQgSYlgwrgVRHU=",
      "lt_id_alb": [
        "63410260"
      ],
      "list_id_nortag": [
        "-467032699",
        "-273690518"
      ],
      "lt_id_sptag": [
        "-1147068729",
        "636212748",
        "707334961",
        "235131583"
      ]
    }
  ],
  "lt_nortag": [
    {
      "id_nortag": "-467032699",
      "name_cl_nortag": "Boy",
      "total_img": 8592,
      "name_parent": "Anime"
    },
    {
      "id_nortag": "1728965817",
      "name_cl_nortag": "Couple",
      "total_img": 2059,
      "name_parent": "Anime"
    },
    {
      "id_nortag": "1213914829",
      "name_cl_nortag": "Crossover",
      "total_img": 505,
      "name_parent": "Anime"
    },
    {
      "id_nortag": "-273690518",
      "name_cl_nortag": "Naruto",
      "total_img": 478,
      "name_parent": "Anime"
    }
  ],
  "lt_sptag": [
    {
      "id_sptag": "-1287948517",
      "name_cl_sptag": "Akame Akame Ga Kill",
      "name_parent": "Anime",
      "total": 46
    },
    {
      "id_sptag": "-336629613",
      "name_cl_sptag": "Archer FateStay Night",
      "name_parent": "Anime",
      "total": 21
    },
    {
      "id_sptag": "755798438",
      "name_cl_sptag": "Asuna Yuuki",
      "name_parent": "Anime",
      "total": 201
    },
    {
      "id_sptag": "1956034203",
      "name_cl_sptag": "Boy Sad",
      "name_parent": "Anime",
      "total": 1551
    },
    {
      "id_sptag": "1483714349",
      "name_cl_sptag": "Byakuya Kuchiki",
      "name_parent": "Anime",
      "total": 36
    },
    {
      "id_sptag": "-1636146762",
      "name_cl_sptag": "Deidara Naruto",
      "name_parent": "Anime",
      "total": 31
    },
    {
      "id_sptag": "1304638402",
      "name_cl_sptag": "Eren Yeager",
      "name_parent": "Anime",
      "total": 294
    },
    {
      "id_sptag": "1341791943",
      "name_cl_sptag": "Erza Scarlet",
      "name_parent": "Anime",
      "total": 39
    },
    {
      "id_sptag": "1339472867",
      "name_cl_sptag": "Fullmetal Alchemist",
      "name_parent": "Anime",
      "total": 7
    },
    {
      "id_sptag": "-437830348",
      "name_cl_sptag": "Gaara Naruto",
      "name_parent": "Anime",
      "total": 40
    },
    {
      "id_sptag": "-1566457957",
      "name_cl_sptag": "Gajeel Redfox",
      "name_parent": "Anime",
      "total": 19
    },
    {
      "id_sptag": "-1194486571",
      "name_cl_sptag": "Gilgamesh Fate Series",
      "name_parent": "Anime",
      "total": 15
    },
    {
      "id_sptag": "1097983947",
      "name_cl_sptag": "Goku",
      "name_parent": "Anime",
      "total": 321
    },
    {
      "id_sptag": "1278412262",
      "name_cl_sptag": "Gray Fullbuster",
      "name_parent": "Anime",
      "total": 32
    },
    {
      "id_sptag": "-1424398522",
      "name_cl_sptag": "Halloween",
      "name_parent": "Anime",
      "total": 70
    },
    {
      "id_sptag": "-801134466",
      "name_cl_sptag": "Hashirama Senju",
      "name_parent": "Anime",
      "total": 3
    },
    {
      "id_sptag": "644020459",
      "name_cl_sptag": "Highschool Of The Dead",
      "name_parent": "Anime",
      "total": 3
    },
    {
      "id_sptag": "-567684239",
      "name_cl_sptag": "Himawari Uzumaki",
      "name_parent": "Anime",
      "total": 30
    },
    {
      "id_sptag": "-1777120776",
      "name_cl_sptag": "Hinata Hyuga",
      "name_parent": "Anime",
      "total": 54
    },
    {
      "id_sptag": "-1477452695",
      "name_cl_sptag": "Ichigo Kurosaki",
      "name_parent": "Anime",
      "total": 201
    },
    {
      "id_sptag": "154930047",
      "name_cl_sptag": "Inori Yuzuriha",
      "name_parent": "Anime",
      "total": 32
    },
    {
      "id_sptag": "-2029145421",
      "name_cl_sptag": "Itachi Uchiha",
      "name_parent": "Anime",
      "total": 58
    },
    {
      "id_sptag": "-356011767",
      "name_cl_sptag": "Jellal Fernandes",
      "name_parent": "Anime",
      "total": 7
    },
    {
      "id_sptag": "-1147068729",
      "name_cl_sptag": "Jiraiya Naruto",
      "name_parent": "Anime",
      "total": 20
    },
    {
      "id_sptag": "639891871",
      "name_cl_sptag": "Kabuto Yakushi",
      "name_parent": "Anime",
      "total": 6
    },
    {
      "id_sptag": "707334961",
      "name_cl_sptag": "Kakashi Hatake",
      "name_parent": "Anime",
      "total": 99
    },
    {
      "id_sptag": "-247566452",
      "name_cl_sptag": "Kanade Tachibana",
      "name_parent": "Anime",
      "total": 216
    },
    {
      "id_sptag": "1510416678",
      "name_cl_sptag": "Kaori Kanzaki",
      "name_parent": "Anime",
      "total": 5
    },
    {
      "id_sptag": "1753469251",
      "name_cl_sptag": "Kaori Miyazono",
      "name_parent": "Anime",
      "total": 138
    },
    {
      "id_sptag": "-1619220508",
      "name_cl_sptag": "Kazuto Kirigaya",
      "name_parent": "Anime",
      "total": 125
    },
    {
      "id_sptag": "1171821264",
      "name_cl_sptag": "Ken Kaneki",
      "name_parent": "Anime",
      "total": 255
    },
    {
      "id_sptag": "105837710",
      "name_cl_sptag": "Kenpachi Zaraki",
      "name_parent": "Anime",
      "total": 23
    },
    {
      "id_sptag": "-1052321700",
      "name_cl_sptag": "Kirito Sword Art Online",
      "name_parent": "Anime",
      "total": 206
    },
    {
      "id_sptag": "1977786894",
      "name_cl_sptag": "Korra The Legend Of Korra",
      "name_parent": "Anime",
      "total": 11
    },
    {
      "id_sptag": "941027275",
      "name_cl_sptag": "Kousei Arima",
      "name_parent": "Anime",
      "total": 59
    },
    {
      "id_sptag": "319237405",
      "name_cl_sptag": "Kurama Naruto",
      "name_parent": "Anime",
      "total": 22
    },
    {
      "id_sptag": "-1102714022",
      "name_cl_sptag": "Kurisu Makise",
      "name_parent": "Anime",
      "total": 38
    },
    {
      "id_sptag": "175619851",
      "name_cl_sptag": "Kurome Akame Ga Kill",
      "name_parent": "Anime",
      "total": 8
    },
    {
      "id_sptag": "-313914664",
      "name_cl_sptag": "Kushina Uzumaki",
      "name_parent": "Anime",
      "total": 13
    },
    {
      "id_sptag": "-1732733924",
      "name_cl_sptag": "Kyubi Naruto",
      "name_parent": "Anime",
      "total": 14
    },
    {
      "id_sptag": "2080340491",
      "name_cl_sptag": "L Death Note",
      "name_parent": "Anime",
      "total": 24
    },
    {
      "id_sptag": "-1236345551",
      "name_cl_sptag": "Levi Ackerman",
      "name_parent": "Anime",
      "total": 232
    },
    {
      "id_sptag": "-916379327",
      "name_cl_sptag": "Madara Uchiha",
      "name_parent": "Anime",
      "total": 21
    },
    {
      "id_sptag": "-1989109578",
      "name_cl_sptag": "Majin Buu",
      "name_parent": "Anime",
      "total": 37
    },
    {
      "id_sptag": "2037558530",
      "name_cl_sptag": "Masami Iwasawa",
      "name_parent": "Anime",
      "total": 27
    },
    {
      "id_sptag": "1169337322",
      "name_cl_sptag": "Mato Kuroi",
      "name_parent": "Anime",
      "total": 19
    },
    {
      "id_sptag": "1484744413",
      "name_cl_sptag": "Mikasa Ackerman",
      "name_parent": "Anime",
      "total": 326
    },
    {
      "id_sptag": "235131583",
      "name_cl_sptag": "Minato Namikaze",
      "name_parent": "Anime",
      "total": 43
    },
    {
      "id_sptag": "-91316480",
      "name_cl_sptag": "Monkey D Luffy",
      "name_parent": "Anime",
      "total": 156
    },
    {
      "id_sptag": "636212748",
      "name_cl_sptag": "Naruto Uzumaki",
      "name_parent": "Anime",
      "total": 292
    },
    {
      "id_sptag": "-1936986648",
      "name_cl_sptag": "Natsu Dragneel",
      "name_parent": "Anime",
      "total": 117
    },
    {
      "id_sptag": "-2020568135",
      "name_cl_sptag": "NineTails Naruto",
      "name_parent": "Anime",
      "total": 4
    },
    {
      "id_sptag": "-1812796880",
      "name_cl_sptag": "Obito Uchiha",
      "name_parent": "Anime",
      "total": 59
    },
    {
      "id_sptag": "-762518597",
      "name_cl_sptag": "Orochimaru Naruto",
      "name_parent": "Anime",
      "total": 12
    },
    {
      "id_sptag": "-555297640",
      "name_cl_sptag": "Portgas D Ace",
      "name_parent": "Anime",
      "total": 48
    },
    {
      "id_sptag": "1083705889",
      "name_cl_sptag": "Pumpkin",
      "name_parent": "Anime",
      "total": 45
    },
    {
      "id_sptag": "1233261441",
      "name_cl_sptag": "Rin Tohsaka",
      "name_parent": "Anime",
      "total": 36
    },
    {
      "id_sptag": "6278890",
      "name_cl_sptag": "Rock Lee",
      "name_parent": "Anime",
      "total": 23
    },
    {
      "id_sptag": "1428433125",
      "name_cl_sptag": "Roronoa Zoro",
      "name_parent": "Anime",
      "total": 75
    },
    {
      "id_sptag": "-855277766",
      "name_cl_sptag": "Ryuk Death Note",
      "name_parent": "Anime",
      "total": 15
    },
    {
      "id_sptag": "-1019873723",
      "name_cl_sptag": "Saber Fate Series",
      "name_parent": "Anime",
      "total": 218
    },
    {
      "id_sptag": "758979432",
      "name_cl_sptag": "Sabo One Piece",
      "name_parent": "Anime",
      "total": 25
    },
    {
      "id_sptag": "-1216236529",
      "name_cl_sptag": "Sad",
      "name_parent": "Anime",
      "total": 12057
    },
    {
      "id_sptag": "-456927585",
      "name_cl_sptag": "Saitama OnePunch Man",
      "name_parent": "Anime",
      "total": 32
    },
    {
      "id_sptag": "-1282606609",
      "name_cl_sptag": "Sakura Haruno",
      "name_parent": "Anime",
      "total": 93
    },
    {
      "id_sptag": "-1612103380",
      "name_cl_sptag": "Sanji One Piece",
      "name_parent": "Anime",
      "total": 74
    },
    {
      "id_sptag": "-1680871127",
      "name_cl_sptag": "Sasori Naruto",
      "name_parent": "Anime",
      "total": 32
    },
    {
      "id_sptag": "120588791",
      "name_cl_sptag": "Sasuke Uchiha",
      "name_parent": "Anime",
      "total": 154
    },
    {
      "id_sptag": "759287130",
      "name_cl_sptag": "Shikamaru Nara",
      "name_parent": "Anime",
      "total": 23
    },
    {
      "id_sptag": "1031977212",
      "name_cl_sptag": "Shingeki No Kyojin",
      "name_parent": "Anime",
      "total": 201
    },
    {
      "id_sptag": "-266713074",
      "name_cl_sptag": "Shinichi Izumi",
      "name_parent": "Anime",
      "total": 6
    },
    {
      "id_sptag": "182755482",
      "name_cl_sptag": "Shino Asada",
      "name_parent": "Anime",
      "total": 34
    },
    {
      "id_sptag": "1275572979",
      "name_cl_sptag": "Shu Ouma",
      "name_parent": "Anime",
      "total": 9
    },
    {
      "id_sptag": "1767521621",
      "name_cl_sptag": "Sinon Sword Art Online",
      "name_parent": "Anime",
      "total": 49
    },
    {
      "id_sptag": "1686539664",
      "name_cl_sptag": "Tony Tony Chopper",
      "name_parent": "Anime",
      "total": 59
    },
    {
      "id_sptag": "-1491861316",
      "name_cl_sptag": "Touka Kirishima",
      "name_parent": "Anime",
      "total": 89
    },
    {
      "id_sptag": "433369509",
      "name_cl_sptag": "Trafalgar Law",
      "name_parent": "Anime",
      "total": 26
    },
    {
      "id_sptag": "1390001312",
      "name_cl_sptag": "Tsunade Naruto",
      "name_parent": "Anime",
      "total": 6
    },
    {
      "id_sptag": "-1092878010",
      "name_cl_sptag": "Ulquiorra Cifer",
      "name_parent": "Anime",
      "total": 34
    },
    {
      "id_sptag": "-1986334657",
      "name_cl_sptag": "Vegeta Dragon Ball",
      "name_parent": "Anime",
      "total": 124
    },
    {
      "id_sptag": "87064186",
      "name_cl_sptag": "Yukino Yukinoshita",
      "name_parent": "Anime",
      "total": 30
    },
    {
      "id_sptag": "253689623",
      "name_cl_sptag": "Yuno Gasai",
      "name_parent": "Anime",
      "total": 18
    },
    {
      "id_sptag": "-678729605",
      "name_cl_sptag": "Yuuki Konno",
      "name_parent": "Anime",
      "total": 40
    },
    {
      "id_sptag": "-2123925318",
      "name_cl_sptag": "Zabuza Momochi",
      "name_parent": "Anime",
      "total": 5
    }
  ]
}